{"name": "Sableye-Mega", "usage": {"name": "Sableye-Mega", "rank": 58, "usage_percent": 2.728}, "base_stats": [50, 85, 125, 85, 115, 20], "types": ["Dark", "Ghost"], "possible_abilities": ["Magic Bounce"], "moves": [{"name": "Will-O-Wisp", "id": "willowisp", "usage_percent": 99.954}, {"name": "Recover", "id": "recover", "usage_percent": 99.412}, {"name": "Knock Off", "id": "knockoff", "usage_percent": 95.667}, {"name": "Protect", "id": "protect", "usage_percent": 94.075}, {"name": "Calm Mind", "id": "calmmind", "usage_percent": 2.971}, {"name": "Hex", "id": "hex", "usage_percent": 2.875}, {"name": "Toxic", "id": "toxic", "usage_percent": 1.322}, {"name": "Taunt", "id": "taunt", "usage_percent": 1.314}, {"name": "Foul Play", "id": "foulplay", "usage_percent": 0.864}, {"name": "Encore", "id": "encore", "usage_percent": 0.757}, {"name": "Fake Out", "id": "fakeout", "usage_percent": 0.594}, {"name": "Dark Pulse", "id": "darkpulse", "usage_percent": 0.125}, {"name": "Shadow Sneak", "id": "shadowsneak", "usage_percent": 0.017}, {"name": "Poltergeist", "id": "poltergeist", "usage_percent": 0.012}, {"name": "Sucker Punch", "id": "suckerpunch", "usage_percent": 0.011}, {"name": "Dazzling Gleam", "id": "dazzlinggleam", "usage_percent": 0.009}, {"name": "Night Shade", "id": "nightshade", "usage_percent": 0.007}, {"name": "Gyro Ball", "id": "gyroball", "usage_percent": 0.004}, {"name": "Nasty Plot", "id": "nastyplot", "usage_percent": 0.002}, {"name": "Shadow Ball", "id": "shadowball", "usage_percent": 0.002}, {"name": "Drain Punch", "id": "drainpunch", "usage_percent": 0.001}, {"name": "Focus Punch", "id": "focuspunch", "usage_percent": 0.001}, {"name": "Ice Punch", "id": "icepunch", "usage_percent": 0.001}, {"name": "Torment", "id": "torment", "usage_percent": 0.001}, {"name": "Shadow Claw", "id": "shadowclaw", "usage_percent": 0.001}, {"name": "Power-Up Punch", "id": "poweruppunch", "usage_percent": 0.001}, {"name": "Power Gem", "id": "powergem", "usage_percent": 0.0}, {"name": "Substitute", "id": "substitute", "usage_percent": 0.0}, {"name": "Brick Break", "id": "brickbreak", "usage_percent": 0.0}, {"name": "Body Slam", "id": "bodyslam", "usage_percent": 0.0}, {"name": "Hidden Power Ice", "id": "hiddenpowerice", "usage_percent": 0.0}, {"name": "Pain Split", "id": "painsplit", "usage_percent": 0.0}, {"name": "Poison Jab", "id": "poisonjab", "usage_percent": 0.0}, {"name": "Hone Claws", "id": "honeclaws", "usage_percent": 0.0}, {"name": "Moonlight", "id": "moonlight", "usage_percent": 0.0}, {"name": "Disable", "id": "disable", "usage_percent": 0.0}, {"name": "Double-Edge", "id": "doubleedge", "usage_percent": 0.0}, {"name": "Spite", "id": "spite", "usage_percent": 0.0}, {"name": "Mean Look", "id": "meanlook", "usage_percent": 0.0}], "teammates": [{"name": "Chansey", "usage_percent": 75.941}, {"name": "Clefable", "usage_percent": 68.45}, {"name": "Skarmory", "usage_percent": 50.968}, {"name": "Gliscor", "usage_percent": 41.5}, {"name": "Corviknight", "usage_percent": 32.774}, {"name": "Volcarona", "usage_percent": 28.93}, {"name": "Seismitoad", "usage_percent": 25.205}, {"name": "Alomomola", "usage_percent": 18.688}, {"name": "Shedinja", "usage_percent": 17.13}, {"name": "Blissey", "usage_percent": 14.154}, {"name": "Amoonguss", "usage_percent": 12.058}, {"name": "Quagsire", "usage_percent": 11.934}, {"name": "Toxapex", "usage_percent": 10.949}, {"name": "Kyurem", "usage_percent": 7.547}, {"name": "Gastrodon", "usage_percent": 6.517}, {"name": "Buzzwole", "usage_percent": 4.161}, {"name": "Greninja", "usage_percent": 3.945}, {"name": "Pyukumuku", "usage_percent": 3.908}, {"name": "Rillaboom", "usage_percent": 3.369}, {"name": "Melmetal", "usage_percent": 2.851}, {"name": "Raboot", "usage_percent": 2.845}, {"name": "Xurkitree", "usage_percent": 2.845}, {"name": "Zapdos", "usage_percent": 2.546}, {"name": "Ferrothorn", "usage_percent": 2.19}, {"name": "Excadrill", "usage_percent": 2.014}, {"name": "Slowbro", "usage_percent": 1.956}, {"name": "Metagross", "usage_percent": 1.385}, {"name": "Celesteela", "usage_percent": 1.157}, {"name": "Ditto", "usage_percent": 1.036}, {"name": "Weezing-Galar", "usage_percent": 1.035}, {"name": "Heatran", "usage_percent": 0.917}, {"name": "Eldegoss", "usage_percent": 0.907}, {"name": "Tangrowth", "usage_percent": 0.66}, {"name": "Tsareena", "usage_percent": 0.626}, {"name": "Tapu Fini", "usage_percent": 0.612}, {"name": "Mimikyu", "usage_percent": 0.538}, {"name": "Corsola-Galar", "usage_percent": 0.538}, {"name": "Arcanine", "usage_percent": 0.341}, {"name": "Landorus-Therian", "usage_percent": 0.291}, {"name": "Deoxys-Defense", "usage_percent": 0.279}, {"name": "Dragonite", "usage_percent": 0.252}, {"name": "Tapu Koko", "usage_percent": 0.234}, {"name": "Slowking-Galar", "usage_percent": 0.223}, {"name": "Kartana", "usage_percent": 0.193}, {"name": "Araquanid", "usage_percent": 0.193}, {"name": "Moltres", "usage_percent": 0.152}, {"name": "Scizor", "usage_percent": 0.119}, {"name": "Nihilego", "usage_percent": 0.114}, {"name": "Magnezone", "usage_percent": 0.105}, {"name": "Urshifu-Rapid-Strike", "usage_percent": 0.102}, {"name": "Latias-Mega", "usage_percent": 0.102}, {"name": "Weavile", "usage_percent": 0.086}, {"name": "Ninetales-Alola", "usage_percent": 0.077}, {"name": "Sandslash-Alola", "usage_percent": 0.068}, {"name": "Nidoking", "usage_percent": 0.061}, {"name": "Wigglytuff", "usage_percent": 0.035}, {"name": "Rotom-Wash", "usage_percent": 0.034}, {"name": "Gengar", "usage_percent": 0.025}, {"name": "Togekiss", "usage_percent": 0.025}, {"name": "Jirachi", "usage_percent": 0.022}, {"name": "Accelgor", "usage_percent": 0.021}, {"name": "Incineroar", "usage_percent": 0.019}, {"name": "Suicune", "usage_percent": 0.017}, {"name": "Cresselia", "usage_percent": 0.017}, {"name": "Arctozolt", "usage_percent": 0.011}, {"name": "Primarina", "usage_percent": 0.011}, {"name": "Breloom", "usage_percent": 0.011}, {"name": "Zapdos-Galar", "usage_percent": 0.009}, {"name": "Cinccino", "usage_percent": 0.007}, {"name": "Alakazam", "usage_percent": 0.007}, {"name": "Porygon-Z", "usage_percent": 0.007}, {"name": "Hoopa-Unbound", "usage_percent": 0.007}, {"name": "Dracozolt", "usage_percent": 0.007}, {"name": "Mienshao", "usage_percent": 0.006}, {"name": "Hippowdon", "usage_percent": 0.004}, {"name": "Sharpedo", "usage_percent": 0.004}, {"name": "Tropius", "usage_percent": 0.003}, {"name": "Galvantula", "usage_percent": 0.002}, {"name": "Regieleki", "usage_percent": 0.002}, {"name": "Swampert", "usage_percent": 0.002}, {"name": "Swellow", "usage_percent": 0.002}, {"name": "Beautifly", "usage_percent": 0.002}, {"name": "Linoone", "usage_percent": 0.002}, {"name": "Rotom-Mow", "usage_percent": 0.001}, {"name": "Crobat", "usage_percent": 0.001}, {"name": "Golisopod", "usage_percent": 0.001}, {"name": "Venusaur-Mega", "usage_percent": 0.001}, {"name": "Drifblim", "usage_percent": 0.001}, {"name": "Chandelure", "usage_percent": 0.001}, {"name": "Eelektross", "usage_percent": 0.001}, {"name": "Drapion", "usage_percent": 0.001}, {"name": "Volcanion", "usage_percent": 0.001}, {"name": "Ninetales", "usage_percent": 0.001}, {"name": "Camerupt-Mega", "usage_percent": 0.0}, {"name": "Tyranitar", "usage_percent": 0.0}, {"name": "Mew", "usage_percent": 0.0}, {"name": "Sceptile", "usage_percent": 0.0}, {"name": "Electivire", "usage_percent": 0.0}, {"name": "Blastoise", "usage_percent": 0.0}, {"name": "Infernape", "usage_percent": 0.0}, {"name": "Thundurus", "usage_percent": 0.0}, {"name": "Gyarados", "usage_percent": 0.0}, {"name": "Klefki", "usage_percent": 0.0}, {"name": "Krookodile", "usage_percent": 0.0}, {"name": "Crawdaunt", "usage_percent": 0.0}, {"name": "Obstagoon", "usage_percent": 0.0}, {"name": "Muk-Alola", "usage_percent": 0.0}, {"name": "Glaceon", "usage_percent": 0.0}, {"name": "Darmanitan", "usage_percent": 0.0}, {"name": "Garchomp", "usage_percent": 0.0}, {"name": "Chesnaught", "usage_percent": 0.0}, {"name": "Lucario", "usage_percent": 0.0}, {"name": "Scolipede", "usage_percent": 0.0}, {"name": "Zoroark", "usage_percent": 0.0}, {"name": "Kommo-o", "usage_percent": 0.0}, {"name": "Gardevoir", "usage_percent": 0.0}, {"name": "Zeraora", "usage_percent": 0.0}, {"name": "Tornadus", "usage_percent": 0.0}, {"name": "Toxtricity", "usage_percent": 0.0}, {"name": "Slaking", "usage_percent": 0.0}, {"name": "Gallade-Mega", "usage_percent": 0.0}, {"name": "Charizard-Mega-Y", "usage_percent": 0.0}, {"name": "Lycanroc-Dusk", "usage_percent": 0.0}, {"name": "Gyarados-Mega", "usage_percent": 0.0}, {"name": "Aegislash", "usage_percent": 0.0}, {"name": "Bastiodon", "usage_percent": 0.0}, {"name": "Sirfetch'd", "usage_percent": 0.0}, {"name": "Sneasel", "usage_percent": 0.0}, {"name": "Mismagius", "usage_percent": 0.0}, {"name": "Spiritomb", "usage_percent": 0.0}, {"name": "Polteageist", "usage_percent": 0.0}, {"name": "Wobbuffet", "usage_percent": 0.0}, {"name": "Gigalith", "usage_percent": 0.0}, {"name": "Cofagrigus", "usage_percent": 0.0}, {"name": "Blacephalon", "usage_percent": 0.0}, {"name": "Mightyena", "usage_percent": 0.0}, {"name": "Scrafty", "usage_percent": 0.0}, {"name": "empty", "usage_percent": 0.0}, {"name": "Silvally-Ghost", "usage_percent": 0.0}, {"name": "Runerigus", "usage_percent": 0.0}, {"name": "Cursola", "usage_percent": 0.0}, {"name": "Trevenant", "usage_percent": 0.0}, {"name": "Ampharos-Mega", "usage_percent": 0.0}, {"name": "Altaria-Mega", "usage_percent": 0.0}, {"name": "Umbreon", "usage_percent": 0.0}, {"name": "Morpeko", "usage_percent": 0.0}, {"name": "Heracross-Mega", "usage_percent": 0.0}, {"name": "Azumarill", "usage_percent": 0.0}, {"name": "Pinsir-Mega", "usage_percent": 0.0}, {"name": "Garchomp-Mega", "usage_percent": 0.0}, {"name": "Vaporeon", "usage_percent": 0.0}, {"name": "Forretress", "usage_percent": 0.0}, {"name": "Mantine", "usage_percent": 0.0}, {"name": "Dusclops", "usage_percent": 0.0}, {"name": "Ribombee", "usage_percent": 0.0}, {"name": "Slurpuff", "usage_percent": 0.0}, {"name": "Gligar", "usage_percent": 0.0}, {"name": "Salazzle", "usage_percent": 0.0}, {"name": "Lopunny", "usage_percent": 0.0}, {"name": "Swampert-Mega", "usage_percent": 0.0}, {"name": "Pelipper", "usage_percent": 0.0}, {"name": "Jellicent", "usage_percent": 0.0}, {"name": "Dusknoir", "usage_percent": 0.0}, {"name": "Stakataka", "usage_percent": 0.0}, {"name": "Tapu Lele", "usage_percent": 0.0}, {"name": "Barraskewda", "usage_percent": 0.0}, {"name": "Mamoswine", "usage_percent": 0.0}, {"name": "Snorlax", "usage_percent": 0.0}, {"name": "Tyranitar-Mega", "usage_percent": 0.0}, {"name": "Regigigas", "usage_percent": 0.0}, {"name": "Pikachu", "usage_percent": 0.0}, {"name": "Kecleon", "usage_percent": 0.0}, {"name": "Hawlucha", "usage_percent": 0.0}, {"name": "Victini", "usage_percent": 0.0}, {"name": "Staraptor", "usage_percent": 0.0}, {"name": "Aron", "usage_percent": 0.0}, {"name": "Kangaskhan", "usage_percent": 0.0}, {"name": "Slowking", "usage_percent": 0.0}, {"name": "Shiinotic", "usage_percent": 0.0}, {"name": "Hydreigon", "usage_percent": 0.0}], "items": [{"name": "Sablenite", "id": "sablenite", "usage_percent": 100.0}], "abilities": [{"name": "Magic Bounce", "id": "magicbounce", "usage_percent": 100.0}], "natures": [{"name": "Careful", "usage_percent": 64.793}, {"name": "Impish", "usage_percent": 31.326}, {"name": "Bold", "usage_percent": 3.317}, {"name": "Calm", "usage_percent": 0.285}, {"name": "Relaxed", "usage_percent": 0.129}, {"name": "Brave", "usage_percent": 0.125}, {"name": "Adamant", "usage_percent": 0.012}, {"name": "Quiet", "usage_percent": 0.009}, {"name": "Lax", "usage_percent": 0.002}, {"name": "Modest", "usage_percent": 0.002}, {"name": "Naughty", "usage_percent": 0.0}, {"name": "Hardy", "usage_percent": 0.0}, {"name": "Sassy", "usage_percent": 0.0}], "spreads": [{"spread": "Careful:248/0/0/0/252/8", "usage_percent": 27.22}, {"spread": "Impish:252/0/252/0/4/0", "usage_percent": 16.696}, {"spread": "Careful:248/0/8/0/248/4", "usage_percent": 12.031}, {"spread": "Careful:252/0/0/0/252/4", "usage_percent": 9.21}, {"spread": "Impish:252/4/0/0/252/0", "usage_percent": 6.195}, {"spread": "Impish:252/0/176/0/80/0", "usage_percent": 5.844}, {"spread": "Careful:252/0/40/0/216/0", "usage_percent": 5.201}, {"spread": "Careful:248/8/0/0/252/0", "usage_percent": 4.409}, {"spread": "Bold:252/0/96/8/152/0", "usage_percent": 2.845}, {"spread": "Careful:248/0/8/0/252/0", "usage_percent": 2.788}, {"spread": "Careful:248/0/84/0/172/4", "usage_percent": 1.904}, {"spread": "Impish:248/0/8/0/248/4", "usage_percent": 1.636}, {"spread": "Careful:252/0/4/0/252/0", "usage_percent": 1.28}], "evs": {"atk": [{"ev_string": "0 Atk", "usage_percent": 85.633}, {"ev_string": "4 Atk", "usage_percent": 6.195}, {"ev_string": "8 Atk", "usage_percent": 4.431}, {"ev_string": "0- Atk", "usage_percent": 3.604}, {"ev_string": "0+ Atk", "usage_percent": 0.124}], "spa": [{"ev_string": "0- SpA", "usage_percent": 96.132}, {"ev_string": "8 SpA", "usage_percent": 2.935}, {"ev_string": "0 SpA", "usage_percent": 0.893}, {"ev_string": "6 SpA", "usage_percent": 0.03}, {"ev_string": "252+ SpA", "usage_percent": 0.011}], "spe": [{"ev_string": "0 Spe", "usage_percent": 47.197}, {"ev_string": "8 Spe", "usage_percent": 27.739}, {"ev_string": "4 Spe", "usage_percent": 24.802}, {"ev_string": "0- Spe", "usage_percent": 0.262}, {"ev_string": "84 Spe", "usage_percent": 0.0}], "hp_def": [{"ev_string": "248 HP / 0 Def", "usage_percent": 31.772}, {"ev_string": "252 HP / 252+ Def", "usage_percent": 17.413}, {"ev_string": "248 HP / 8 Def", "usage_percent": 14.818}, {"ev_string": "252 HP / 0 Def", "usage_percent": 9.21}, {"ev_string": "252 HP / 0+ Def", "usage_percent": 6.195}, {"ev_string": "252 HP / 176+ Def", "usage_percent": 5.844}, {"ev_string": "252 HP / 40 Def", "usage_percent": 5.201}, {"ev_string": "252 HP / 96+ Def", "usage_percent": 2.845}, {"ev_string": "248 HP / 84 Def", "usage_percent": 1.904}, {"ev_string": "248 HP / 8+ Def", "usage_percent": 1.636}, {"ev_string": "252 HP / 4 Def", "usage_percent": 1.412}], "hp_spd": [{"ev_string": "248 HP / 252+ SpD", "usage_percent": 34.536}, {"ev_string": "252 HP / 4 SpD", "usage_percent": 17.396}, {"ev_string": "248 HP / 248+ SpD", "usage_percent": 12.031}, {"ev_string": "252 HP / 252+ SpD", "usage_percent": 10.621}, {"ev_string": "252 HP / 252 SpD", "usage_percent": 6.195}, {"ev_string": "252 HP / 80 SpD", "usage_percent": 5.844}, {"ev_string": "252 HP / 216+ SpD", "usage_percent": 5.201}, {"ev_string": "252 HP / 152 SpD", "usage_percent": 2.845}, {"ev_string": "248 HP / 172+ SpD", "usage_percent": 1.904}, {"ev_string": "248 HP / 248 SpD", "usage_percent": 1.636}]}, "tera_types": [{"tera_type": "Nothing", "usage_percent": 100.0}], "counters": [], "dominates": [], "rating": 1760}