{"name": "Sandy Shocks", "usage": {"name": "Sandy Shocks", "rank": 196, "usage_percent": 0.311}, "base_stats": [85, 81, 97, 121, 85, 101], "types": ["Electric", "Ground"], "possible_abilities": ["Protosynthesis"], "moves": [{"name": "Sandsear Storm", "id": "sandsearstorm", "usage_percent": 81.437}, {"name": "Volt Switch", "id": "voltswitch", "usage_percent": 41.192}, {"name": "Rising Voltage", "id": "risingvoltage", "usage_percent": 40.584}, {"name": "Stealth Rock", "id": "stealthrock", "usage_percent": 38.24}, {"name": "Electro Drift", "id": "electrodrift", "usage_percent": 36.847}, {"name": "Gravity", "id": "gravity", "usage_percent": 26.142}, {"name": "Wildbolt Storm", "id": "wildboltstorm", "usage_percent": 24.432}, {"name": "Earth Power", "id": "earthpower", "usage_percent": 18.563}, {"name": "Thunderclap", "id": "thunderclap", "usage_percent": 18.223}, {"name": "Flash Cannon", "id": "flashcannon", "usage_percent": 17.394}, {"name": "Thunder", "id": "thunder", "usage_percent": 15.873}, {"name": "Nuzzle", "id": "nuzzle", "usage_percent": 14.442}, {"name": "Parabolic Charge", "id": "paraboliccharge", "usage_percent": 8.406}, {"name": "Mirror Coat", "id": "mirrorcoat", "usage_percent": 8.406}, {"name": "Light Screen", "id": "lightscreen", "usage_percent": 7.204}, {"name": "Shore Up", "id": "shoreup", "usage_percent": 2.065}, {"name": "Spikes", "id": "spikes", "usage_percent": 0.548}], "teammates": [{"name": "Magnezone", "usage_percent": 50.574}, {"name": "Pelipper", "usage_percent": 40.305}, {"name": "Gallade", "usage_percent": 35.42}, {"name": "Pincurchin", "usage_percent": 35.42}, {"name": "Volcarona", "usage_percent": 29.094}, {"name": "Rotom-Wash", "usage_percent": 26.142}, {"name": "Poliwrath", "usage_percent": 24.432}, {"name": "Pecharunt", "usage_percent": 24.432}, {"name": "Gliscor", "usage_percent": 24.432}, {"name": "Heatran", "usage_percent": 15.611}, {"name": "Yanmega", "usage_percent": 15.611}, {"name": "Grafaiai", "usage_percent": 15.611}, {"name": "Azelf", "usage_percent": 15.611}, {"name": "Jumpluff", "usage_percent": 15.611}, {"name": "Walking Wake", "usage_percent": 13.808}, {"name": "Palafin", "usage_percent": 13.808}, {"name": "Scizor", "usage_percent": 13.808}, {"name": "Archaludon", "usage_percent": 13.808}, {"name": "Iron Moth", "usage_percent": 9.278}, {"name": "Iron Boulder", "usage_percent": 9.278}, {"name": "Iron Treads", "usage_percent": 9.278}, {"name": "Iron Valiant", "usage_percent": 5.301}, {"name": "Salamence", "usage_percent": 2.952}, {"name": "Toxapex", "usage_percent": 2.952}, {"name": "Crawdaunt", "usage_percent": 2.952}, {"name": "Alomomola", "usage_percent": 2.065}, {"name": "Ludicolo", "usage_percent": 2.065}, {"name": "Hydrapple", "usage_percent": 2.065}, {"name": "Araquanid", "usage_percent": 0.284}, {"name": "Corviknight", "usage_percent": 0.284}, {"name": "Blaziken", "usage_percent": 0.284}, {"name": "Ogerpon-Cornerstone", "usage_percent": 0.284}], "items": [{"name": "Booster Energy", "id": "boosterenergy", "usage_percent": 49.853}, {"name": "Heavy-Duty Boots", "id": "heavydutyboots", "usage_percent": 38.24}, {"name": "Leftovers", "id": "leftovers", "usage_percent": 8.406}, {"name": "Choice Scarf", "id": "choicescarf", "usage_percent": 2.952}, {"name": "Power Herb", "id": "powerherb", "usage_percent": 0.424}, {"name": "Wide Lens", "id": "widelens", "usage_percent": 0.124}], "abilities": [{"name": "Protosynthesis", "id": "protosynthesis", "usage_percent": 100.0}], "natures": [{"name": "Timid", "usage_percent": 66.995}, {"name": "Naive", "usage_percent": 14.442}, {"name": "Modest", "usage_percent": 10.157}, {"name": "Calm", "usage_percent": 8.406}], "spreads": [{"spread": "Timid:0/0/0/252/4/252", "usage_percent": 38.788}, {"spread": "Timid:72/0/0/180/4/252", "usage_percent": 26.142}, {"spread": "Naive:0/4/0/252/0/252", "usage_percent": 14.442}, {"spread": "Modest:4/0/0/252/0/252", "usage_percent": 10.157}, {"spread": "Calm:252/0/0/4/252/0", "usage_percent": 8.406}, {"spread": "Timid:48/0/0/208/0/252", "usage_percent": 2.065}], "evs": {"atk": [{"ev_string": "0- Atk", "usage_percent": 85.558}, {"ev_string": "4 Atk", "usage_percent": 14.442}], "spa": [{"ev_string": "252 SpA", "usage_percent": 53.23}, {"ev_string": "180 SpA", "usage_percent": 26.142}, {"ev_string": "252+ SpA", "usage_percent": 10.157}, {"ev_string": "4 SpA", "usage_percent": 8.406}, {"ev_string": "208 SpA", "usage_percent": 2.065}], "spe": [{"ev_string": "252+ Spe", "usage_percent": 81.437}, {"ev_string": "252 Spe", "usage_percent": 10.157}, {"ev_string": "0 Spe", "usage_percent": 8.406}], "hp_def": [{"ev_string": "0 HP / 0 Def", "usage_percent": 53.23}, {"ev_string": "72 HP / 0 Def", "usage_percent": 26.142}, {"ev_string": "4 HP / 0 Def", "usage_percent": 10.157}, {"ev_string": "252 HP / 0 Def", "usage_percent": 8.406}, {"ev_string": "48 HP / 0 Def", "usage_percent": 2.065}], "hp_spd": [{"ev_string": "0 HP / 4 SpD", "usage_percent": 38.788}, {"ev_string": "72 HP / 4 SpD", "usage_percent": 26.142}, {"ev_string": "0 HP / 0- SpD", "usage_percent": 14.442}, {"ev_string": "4 HP / 0 SpD", "usage_percent": 10.157}, {"ev_string": "252 HP / 252+ SpD", "usage_percent": 8.406}, {"ev_string": "48 HP / 0 SpD", "usage_percent": 2.065}]}, "tera_types": [{"tera_type": "Nothing", "usage_percent": 100.0}], "counters": [], "dominates": [], "rating": 1500}