{"name": "Serperior", "usage": {"name": "Serperior", "rank": 46, "usage_percent": 3.979}, "base_stats": [75, 75, 95, 75, 95, 113], "types": ["Grass"], "possible_abilities": ["Overgrow", "Contrary"], "moves": [{"name": "Leaf Storm", "id": "leafstorm", "usage_percent": 99.945}, {"name": "Hidden Power Fire", "id": "hiddenpowerfire", "usage_percent": 88.202}, {"name": "Glare", "id": "glare", "usage_percent": 59.844}, {"name": "Hyper Beam", "id": "hyperbeam", "usage_percent": 43.135}, {"name": "Substitute", "id": "substitute", "usage_percent": 39.768}, {"name": "Leech Seed", "id": "leechseed", "usage_percent": 19.231}, {"name": "Taunt", "id": "taunt", "usage_percent": 18.97}, {"name": "Synthesis", "id": "synthesis", "usage_percent": 12.409}, {"name": "Defog", "id": "defog", "usage_percent": 9.271}, {"name": "Hidden Power Ground", "id": "hiddenpowerground", "usage_percent": 3.362}, {"name": "Dragon Pulse", "id": "dragonpulse", "usage_percent": 3.086}, {"name": "Protect", "id": "protect", "usage_percent": 1.028}, {"name": "Hidden Power Fighting", "id": "hiddenpowerfighting", "usage_percent": 0.599}, {"name": "Knock Off", "id": "knockoff", "usage_percent": 0.4}, {"name": "Reflect", "id": "reflect", "usage_percent": 0.225}, {"name": "Light Screen", "id": "lightscreen", "usage_percent": 0.225}, {"name": "Giga Drain", "id": "gigadrain", "usage_percent": 0.109}, {"name": "Tera Blast", "id": "terablast", "usage_percent": 0.05}, {"name": "Leaf Blade", "id": "leafblade", "usage_percent": 0.04}, {"name": "Hidden Power Ice", "id": "hiddenpowerice", "usage_percent": 0.026}, {"name": "Iron Tail", "id": "irontail", "usage_percent": 0.017}, {"name": "Scale Shot", "id": "scaleshot", "usage_percent": 0.016}, {"name": "Coil", "id": "coil", "usage_percent": 0.016}, {"name": "Bullet Seed", "id": "bulletseed", "usage_percent": 0.016}, {"name": "Aromatherapy", "id": "aromatherapy", "usage_percent": 0.005}, {"name": "Double-Edge", "id": "doubleedge", "usage_percent": 0.002}, {"name": "", "id": "", "usage_percent": 0.001}, {"name": "Energy Ball", "id": "energyball", "usage_percent": 0.001}, {"name": "Calm Mind", "id": "calmmind", "usage_percent": 0.001}, {"name": "Toxic", "id": "toxic", "usage_percent": 0.001}, {"name": "Body Slam", "id": "bodyslam", "usage_percent": 0.0}, {"name": "Hidden Power Flying", "id": "hiddenpowerflying", "usage_percent": 0.0}, {"name": "Mirror Coat", "id": "mirrorcoat", "usage_percent": 0.0}, {"name": "Hidden Power Water", "id": "hiddenpowerwater", "usage_percent": 0.0}, {"name": "Dragon Tail", "id": "dragontail", "usage_percent": 0.0}, {"name": "Petal Blizzard", "id": "petalblizzard", "usage_percent": 0.0}, {"name": "Aqua Tail", "id": "aquatail", "usage_percent": 0.0}, {"name": "Swords Dance", "id": "swordsdance", "usage_percent": 0.0}, {"name": "Cut", "id": "cut", "usage_percent": 0.0}, {"name": "Hidden Power Rock", "id": "hiddenpowerrock", "usage_percent": 0.0}, {"name": "Facade", "id": "facade", "usage_percent": 0.0}, {"name": "Outrage", "id": "outrage", "usage_percent": 0.0}, {"name": "Hidden Power Electric", "id": "hiddenpowerelectric", "usage_percent": 0.0}, {"name": "Hidden Power Steel", "id": "hiddenpowersteel", "usage_percent": 0.0}], "teammates": [{"name": "Iron Moth", "usage_percent": 32.348}, {"name": "Mew", "usage_percent": 27.918}, {"name": "Aegislash", "usage_percent": 26.898}, {"name": "Excadrill", "usage_percent": 21.95}, {"name": "Quaquaval", "usage_percent": 20.814}, {"name": "Ursaluna", "usage_percent": 20.737}, {"name": "Iron Boulder", "usage_percent": 19.842}, {"name": "Bisharp", "usage_percent": 19.175}, {"name": "Celesteela", "usage_percent": 18.233}, {"name": "Gardevoir-Mega", "usage_percent": 17.722}, {"name": "Tyranitar", "usage_percent": 17.084}, {"name": "Thundurus", "usage_percent": 16.661}, {"name": "Araquanid", "usage_percent": 16.272}, {"name": "Swampert", "usage_percent": 16.049}, {"name": "Sharpedo-Mega", "usage_percent": 16.011}, {"name": "Skarmory", "usage_percent": 13.242}, {"name": "Haxorus", "usage_percent": 13.109}, {"name": "Aerodactyl-Mega", "usage_percent": 12.956}, {"name": "Incineroar", "usage_percent": 12.726}, {"name": "Clefable", "usage_percent": 9.887}, {"name": "Keldeo", "usage_percent": 9.828}, {"name": "Victini", "usage_percent": 9.517}, {"name": "Scizor", "usage_percent": 9.036}, {"name": "Rotom-Wash", "usage_percent": 6.854}, {"name": "Tapu Fini", "usage_percent": 6.129}, {"name": "Porygon-Z", "usage_percent": 6.125}, {"name": "Hydreigon", "usage_percent": 4.098}, {"name": "Slowbro", "usage_percent": 4.053}, {"name": "Pecharunt", "usage_percent": 3.687}, {"name": "Hippowdon", "usage_percent": 3.468}, {"name": "Metagross", "usage_percent": 3.361}, {"name": "Latias-Mega", "usage_percent": 3.236}, {"name": "Banette-Mega", "usage_percent": 3.114}, {"name": "Regieleki", "usage_percent": 3.111}, {"name": "Lokix", "usage_percent": 2.872}, {"name": "Zeraora", "usage_percent": 2.732}, {"name": "Mienshao", "usage_percent": 2.488}, {"name": "Glimmora", "usage_percent": 2.435}, {"name": "Salamence", "usage_percent": 2.094}, {"name": "Beedrill-Mega", "usage_percent": 2.002}, {"name": "Magnezone", "usage_percent": 1.513}, {"name": "Archaludon", "usage_percent": 1.371}, {"name": "Rillaboom", "usage_percent": 0.973}, {"name": "Azumarill", "usage_percent": 0.935}, {"name": "Nihilego", "usage_percent": 0.934}, {"name": "Scolipede", "usage_percent": 0.894}, {"name": "Blacephalon", "usage_percent": 0.883}, {"name": "Zygarde-10%", "usage_percent": 0.744}, {"name": "Slowbro-Mega", "usage_percent": 0.506}, {"name": "Mamoswine", "usage_percent": 0.415}, {"name": "Houndoom-Mega", "usage_percent": 0.39}, {"name": "Dracozolt", "usage_percent": 0.377}, {"name": "Garganacl", "usage_percent": 0.251}, {"name": "Heracross-Mega", "usage_percent": 0.227}, {"name": "Ribombee", "usage_percent": 0.222}, {"name": "Sirfetch'd", "usage_percent": 0.191}, {"name": "Jolteon", "usage_percent": 0.191}, {"name": "Cramorant", "usage_percent": 0.191}, {"name": "Darmanitan", "usage_percent": 0.15}, {"name": "Jellicent", "usage_percent": 0.15}, {"name": "Arcanine-Hisui", "usage_percent": 0.149}, {"name": "Chansey", "usage_percent": 0.134}, {"name": "Altaria-Mega", "usage_percent": 0.101}, {"name": "Sableye-Mega", "usage_percent": 0.099}, {"name": "Swampert-Mega", "usage_percent": 0.09}, {"name": "Mandibuzz", "usage_percent": 0.084}, {"name": "Gastrodon", "usage_percent": 0.084}, {"name": "Noivern", "usage_percent": 0.084}, {"name": "Blissey", "usage_percent": 0.081}, {"name": "Manectric-Mega", "usage_percent": 0.079}, {"name": "Toxtricity", "usage_percent": 0.058}, {"name": "Slurpuff", "usage_percent": 0.058}, {"name": "Rapidash", "usage_percent": 0.055}, {"name": "Galvantula", "usage_percent": 0.055}, {"name": "Cresselia", "usage_percent": 0.037}, {"name": "Volcanion", "usage_percent": 0.037}, {"name": "Mimikyu", "usage_percent": 0.037}, {"name": "Buzzwole", "usage_percent": 0.024}, {"name": "Emboar", "usage_percent": 0.024}, {"name": "Cinccino", "usage_percent": 0.016}, {"name": "Samurott", "usage_percent": 0.016}, {"name": "Braviary-Hisui", "usage_percent": 0.016}, {"name": "Mantine", "usage_percent": 0.012}, {"name": "Gengar", "usage_percent": 0.012}, {"name": "Arcanine", "usage_percent": 0.012}, {"name": "Bronzong", "usage_percent": 0.01}, {"name": "Dusknoir", "usage_percent": 0.01}, {"name": "Drapion", "usage_percent": 0.01}, {"name": "Gallade", "usage_percent": 0.009}, {"name": "Jirachi", "usage_percent": 0.009}, {"name": "Shuckle", "usage_percent": 0.008}, {"name": "Crawdaunt", "usage_percent": 0.008}, {"name": "Milotic", "usage_percent": 0.008}, {"name": "Swellow", "usage_percent": 0.008}, {"name": "Quagsire", "usage_percent": 0.007}, {"name": "Ditto", "usage_percent": 0.007}, {"name": "Aggron-Mega", "usage_percent": 0.003}, {"name": "Ambipom", "usage_percent": 0.003}, {"name": "Primarina", "usage_percent": 0.003}, {"name": "Golurk", "usage_percent": 0.002}, {"name": "Zoroark-Hisui", "usage_percent": 0.001}, {"name": "Electrode", "usage_percent": 0.001}, {"name": "Luxray", "usage_percent": 0.001}, {"name": "Orbeetle", "usage_percent": 0.001}, {"name": "Centiskorch", "usage_percent": 0.001}, {"name": "Pidgeot-Mega", "usage_percent": 0.001}, {"name": "Diggersby", "usage_percent": 0.001}, {"name": "Snorlax", "usage_percent": 0.0}, {"name": "Slowking", "usage_percent": 0.0}, {"name": "Whimsicott", "usage_percent": 0.0}, {"name": "Sandy Shocks", "usage_percent": 0.0}, {"name": "Sylveon", "usage_percent": 0.0}, {"name": "Cloyster", "usage_percent": 0.0}, {"name": "Polteageist", "usage_percent": 0.0}, {"name": "Florges", "usage_percent": 0.0}, {"name": "Salazzle", "usage_percent": 0.0}, {"name": "Alakazam", "usage_percent": 0.0}, {"name": "Latias", "usage_percent": 0.0}, {"name": "Togekiss", "usage_percent": 0.0}, {"name": "Infernape", "usage_percent": 0.0}, {"name": "Tauros-Paldea-Blaze", "usage_percent": 0.0}, {"name": "Conkeldurr", "usage_percent": 0.0}, {"name": "Staraptor", "usage_percent": 0.0}, {"name": "Krookodile", "usage_percent": 0.0}, {"name": "Mesprit", "usage_percent": 0.0}, {"name": "Meloetta", "usage_percent": 0.0}, {"name": "Golisopod", "usage_percent": 0.0}, {"name": "Ninetales-Alola", "usage_percent": 0.0}, {"name": "Slowbro-Galar", "usage_percent": 0.0}, {"name": "Tauros-Paldea-Aqua", "usage_percent": 0.0}, {"name": "Runerigus", "usage_percent": 0.0}, {"name": "Zoroark", "usage_percent": 0.0}, {"name": "Arbok", "usage_percent": 0.0}, {"name": "Goodra-Hisui", "usage_percent": 0.0}, {"name": "Azelf", "usage_percent": 0.0}, {"name": "Deoxys-Defense", "usage_percent": 0.0}, {"name": "Maushold", "usage_percent": 0.0}, {"name": "Okidogi", "usage_percent": 0.0}, {"name": "Starmie", "usage_percent": 0.0}, {"name": "Sharpedo", "usage_percent": 0.0}, {"name": "Uxie", "usage_percent": 0.0}, {"name": "Mabosstiff", "usage_percent": 0.0}, {"name": "Empoleon", "usage_percent": 0.0}, {"name": "Sneasel", "usage_percent": 0.0}, {"name": "Moltres-Galar", "usage_percent": 0.0}, {"name": "Smeargle", "usage_percent": 0.0}, {"name": "Enamorus", "usage_percent": 0.0}, {"name": "Malamar", "usage_percent": 0.0}, {"name": "Barraskewda", "usage_percent": 0.0}, {"name": "Cofagrigus", "usage_percent": 0.0}, {"name": "Nidoking", "usage_percent": 0.0}, {"name": "Skeledirge", "usage_percent": 0.0}, {"name": "Ogerpon", "usage_percent": 0.0}, {"name": "Camerupt-Mega", "usage_percent": 0.0}, {"name": "Terrakion", "usage_percent": 0.0}, {"name": "Sigilyph", "usage_percent": 0.0}, {"name": "Zebstrika", "usage_percent": 0.0}, {"name": "Throh", "usage_percent": 0.0}, {"name": "Seismitoad", "usage_percent": 0.0}, {"name": "Chandelure", "usage_percent": 0.0}, {"name": "Fezandipiti", "usage_percent": 0.0}, {"name": "Articuno-Galar", "usage_percent": 0.0}, {"name": "Sandslash-Alola", "usage_percent": 0.0}, {"name": "Ampharos-Mega", "usage_percent": 0.0}, {"name": "Aurorus", "usage_percent": 0.0}, {"name": "Breloom", "usage_percent": 0.0}, {"name": "Arctozolt", "usage_percent": 0.0}, {"name": "Bombirdier", "usage_percent": 0.0}, {"name": "Gigalith", "usage_percent": 0.0}, {"name": "Talonflame", "usage_percent": 0.0}, {"name": "Inteleon", "usage_percent": 0.0}, {"name": "Kingdra", "usage_percent": 0.0}, {"name": "Minior", "usage_percent": 0.0}, {"name": "Lucario", "usage_percent": 0.0}, {"name": "Charizard", "usage_percent": 0.0}, {"name": "Cetitan", "usage_percent": 0.0}, {"name": "Arctovish", "usage_percent": 0.0}, {"name": "Marowak-Alola", "usage_percent": 0.0}, {"name": "Kleavor", "usage_percent": 0.0}, {"name": "Duraludon", "usage_percent": 0.0}, {"name": "Weezing-Galar", "usage_percent": 0.0}, {"name": "empty", "usage_percent": 0.0}, {"name": "Venusaur-Mega", "usage_percent": 0.0}, {"name": "Glaceon", "usage_percent": 0.0}, {"name": "Amoonguss", "usage_percent": 0.0}, {"name": "Glalie-Mega", "usage_percent": 0.0}, {"name": "Eevee", "usage_percent": 0.0}, {"name": "Arboliva", "usage_percent": 0.0}, {"name": "Bibarel", "usage_percent": 0.0}, {"name": "Castform", "usage_percent": 0.0}, {"name": "Torkoal", "usage_percent": 0.0}, {"name": "Lycanroc", "usage_percent": 0.0}, {"name": "Tentacruel", "usage_percent": 0.0}, {"name": "Absol-Mega", "usage_percent": 0.0}, {"name": "Shedinja", "usage_percent": 0.0}, {"name": "Roserade", "usage_percent": 0.0}, {"name": "Hariyama", "usage_percent": 0.0}, {"name": "Iron Jugulis", "usage_percent": 0.0}, {"name": "Chatot", "usage_percent": 0.0}, {"name": "Granbull", "usage_percent": 0.0}, {"name": "Delphox", "usage_percent": 0.0}, {"name": "Gogoat", "usage_percent": 0.0}, {"name": "Porygon2", "usage_percent": 0.0}, {"name": "Steelix-Mega", "usage_percent": 0.0}, {"name": "Entei", "usage_percent": 0.0}], "items": [{"name": "Leftovers", "id": "leftovers", "usage_percent": 44.759}, {"name": "Normalium Z", "id": "normaliumz", "usage_percent": 42.943}, {"name": "Heavy-Duty Boots", "id": "heavydutyboots", "usage_percent": 7.256}, {"name": "Covert Cloak", "id": "covertcloak", "usage_percent": 3.574}, {"name": "Life Orb", "id": "lifeorb", "usage_percent": 0.747}, {"name": "Wide Lens", "id": "widelens", "usage_percent": 0.246}, {"name": "Mental Herb", "id": "mentalherb", "usage_percent": 0.225}, {"name": "Choice Scarf", "id": "choicescarf", "usage_percent": 0.17}, {"name": "Assault Vest", "id": "assaultvest", "usage_percent": 0.034}, {"name": "Focus Sash", "id": "focussash", "usage_percent": 0.028}, {"name": "Loaded Dice", "id": "loadeddice", "usage_percent": 0.016}, {"name": "Choice Specs", "id": "choicespecs", "usage_percent": 0.001}, {"name": "Rocky Helmet", "id": "rockyhelmet", "usage_percent": 0.001}, {"name": "Meadow Plate", "id": "meadowplate", "usage_percent": 0.0}, {"name": "Draco Plate", "id": "dracoplate", "usage_percent": 0.0}, {"name": "Normal Gem", "id": "normalgem", "usage_percent": 0.0}, {"name": "Sitrus Berry", "id": "sitrusberry", "usage_percent": 0.0}, {"name": "Metronome", "id": "metronome", "usage_percent": 0.0}, {"name": "nothing", "id": "nothing", "usage_percent": 0.0}, {"name": "Dragonium Z", "id": "dragoniumz", "usage_percent": 0.0}, {"name": "Dragon Fang", "id": "dragonfang", "usage_percent": 0.0}, {"name": "Icium Z", "id": "iciumz", "usage_percent": 0.0}, {"name": "Grassium Z", "id": "grassiumz", "usage_percent": 0.0}, {"name": "Red Card", "id": "redcard", "usage_percent": 0.0}], "abilities": [{"name": "Contrary", "id": "contrary", "usage_percent": 99.984}, {"name": "Overgrow", "id": "overgrow", "usage_percent": 0.016}], "natures": [{"name": "Timid", "usage_percent": 99.888}, {"name": "Hasty", "usage_percent": 0.07}, {"name": "Jolly", "usage_percent": 0.016}, {"name": "Modest", "usage_percent": 0.011}, {"name": "Hardy", "usage_percent": 0.01}, {"name": "Serious", "usage_percent": 0.004}, {"name": "Bold", "usage_percent": 0.0}, {"name": "Quiet", "usage_percent": 0.0}, {"name": "Mild", "usage_percent": 0.0}, {"name": "Lonely", "usage_percent": 0.0}, {"name": "Bashful", "usage_percent": 0.0}, {"name": "Adamant", "usage_percent": 0.0}], "spreads": [{"spread": "Timid:56/0/0/200/0/252", "usage_percent": 43.328}, {"spread": "Timid:0/0/0/252/4/252", "usage_percent": 38.52}, {"spread": "Timid:164/0/0/92/0/252", "usage_percent": 7.2}, {"spread": "Timid:176/0/0/80/0/252", "usage_percent": 3.173}, {"spread": "Timid:0/0/40/252/0/216", "usage_percent": 3.111}, {"spread": "Timid:24/0/96/156/0/232", "usage_percent": 1.164}], "evs": {"atk": [{"ev_string": "0- Atk", "usage_percent": 99.899}, {"ev_string": "4 Atk", "usage_percent": 0.07}, {"ev_string": "252 Atk", "usage_percent": 0.016}, {"ev_string": "0 Atk", "usage_percent": 0.015}, {"ev_string": "4+ Atk", "usage_percent": 0.0}], "spa": [{"ev_string": "200 SpA", "usage_percent": 43.328}, {"ev_string": "252 SpA", "usage_percent": 43.123}, {"ev_string": "92 SpA", "usage_percent": 7.2}, {"ev_string": "80 SpA", "usage_percent": 3.173}, {"ev_string": "156 SpA", "usage_percent": 1.164}], "spe": [{"ev_string": "252+ Spe", "usage_percent": 95.698}, {"ev_string": "216+ Spe", "usage_percent": 3.111}, {"ev_string": "232+ Spe", "usage_percent": 1.165}, {"ev_string": "252 Spe", "usage_percent": 0.022}, {"ev_string": "4 Spe", "usage_percent": 0.004}], "hp_def": [{"ev_string": "56 HP / 0 Def", "usage_percent": 43.328}, {"ev_string": "0 HP / 0 Def", "usage_percent": 39.366}, {"ev_string": "164 HP / 0 Def", "usage_percent": 7.2}, {"ev_string": "176 HP / 0 Def", "usage_percent": 3.173}, {"ev_string": "0 HP / 40 Def", "usage_percent": 3.111}, {"ev_string": "24 HP / 96 Def", "usage_percent": 1.164}], "hp_spd": [{"ev_string": "56 HP / 0 SpD", "usage_percent": 43.328}, {"ev_string": "0 HP / 4 SpD", "usage_percent": 38.543}, {"ev_string": "164 HP / 0 SpD", "usage_percent": 7.2}, {"ev_string": "0 HP / 0 SpD", "usage_percent": 4.315}, {"ev_string": "176 HP / 0 SpD", "usage_percent": 3.173}, {"ev_string": "24 HP / 0 SpD", "usage_percent": 1.164}]}, "tera_types": [{"tera_type": "Nothing", "usage_percent": 100.0}], "counters": [], "dominates": [], "rating": 1760}