{"name": "Marowak-Alola", "usage": {"name": "Marowak-Alola", "rank": 176, "usage_percent": 0.56}, "base_stats": [60, 80, 110, 50, 80, 45], "types": ["Fire", "Ghost"], "possible_abilities": ["Cursed Body", "Lightning Rod", "Rock Head"], "moves": [{"name": "Flare Blitz", "id": "flareblitz", "usage_percent": 99.989}, {"name": "Poltergeist", "id": "poltergeist", "usage_percent": 85.584}, {"name": "Earthquake", "id": "earthquake", "usage_percent": 79.427}, {"name": "Low Kick", "id": "lowkick", "usage_percent": 45.904}, {"name": "Bonemerang", "id": "bonemerang", "usage_percent": 19.604}, {"name": "Brick Break", "id": "brickbreak", "usage_percent": 18.68}, {"name": "Shadow Bone", "id": "shadowbone", "usage_percent": 14.394}, {"name": "Flame Charge", "id": "flamecharge", "usage_percent": 14.257}, {"name": "Knock Off", "id": "knockoff", "usage_percent": 10.112}, {"name": "Thunder Punch", "id": "thunderpunch", "usage_percent": 4.89}, {"name": "Will-O-Wisp", "id": "willowisp", "usage_percent": 2.875}, {"name": "Swords Dance", "id": "swordsdance", "usage_percent": 1.708}, {"name": "Outrage", "id": "outrage", "usage_percent": 0.753}, {"name": "Focus Punch", "id": "focuspunch", "usage_percent": 0.712}, {"name": "Substitute", "id": "substitute", "usage_percent": 0.528}, {"name": "Iron Head", "id": "ironhead", "usage_percent": 0.152}, {"name": "Double-Edge", "id": "doubleedge", "usage_percent": 0.15}, {"name": "Stealth Rock", "id": "stealthrock", "usage_percent": 0.123}, {"name": "Stone Edge", "id": "stoneedge", "usage_percent": 0.118}, {"name": "Throat Chop", "id": "throatchop", "usage_percent": 0.024}, {"name": "Rock Slide", "id": "rockslide", "usage_percent": 0.007}, {"name": "Bone Rush", "id": "bonerush", "usage_percent": 0.003}, {"name": "Pain Split", "id": "painsplit", "usage_percent": 0.002}, {"name": "Protect", "id": "protect", "usage_percent": 0.002}, {"name": "Power-Up Punch", "id": "poweruppunch", "usage_percent": 0.0}, {"name": "Fire Punch", "id": "firepunch", "usage_percent": 0.0}, {"name": "Submission", "id": "submission", "usage_percent": 0.0}, {"name": "Blizzard", "id": "blizzard", "usage_percent": 0.0}, {"name": "Fire Blast", "id": "fireblast", "usage_percent": 0.0}, {"name": "Shadow Ball", "id": "shadowball", "usage_percent": 0.0}, {"name": "Stomping Tantrum", "id": "stompingtantrum", "usage_percent": 0.0}, {"name": "Curse", "id": "curse", "usage_percent": 0.0}, {"name": "Endeavor", "id": "endeavor", "usage_percent": 0.0}, {"name": "Bone Club", "id": "boneclub", "usage_percent": 0.0}], "teammates": [{"name": "Mimikyu", "usage_percent": 70.291}, {"name": "Runerigus", "usage_percent": 39.0}, {"name": "Gholdengo", "usage_percent": 38.137}, {"name": "Dhelmise", "usage_percent": 38.075}, {"name": "Spiritomb", "usage_percent": 38.074}, {"name": "Zoroark-Hisui", "usage_percent": 29.897}, {"name": "Banette-Mega", "usage_percent": 25.189}, {"name": "Trevenant", "usage_percent": 19.887}, {"name": "Chandelure", "usage_percent": 18.803}, {"name": "Gengar", "usage_percent": 13.579}, {"name": "Corsola-Galar", "usage_percent": 13.484}, {"name": "Volcanion", "usage_percent": 12.991}, {"name": "Arcanine-Hisui", "usage_percent": 9.628}, {"name": "Hoopa", "usage_percent": 9.171}, {"name": "Golurk", "usage_percent": 8.658}, {"name": "Victini", "usage_percent": 8.302}, {"name": "Camerupt-Mega", "usage_percent": 8.119}, {"name": "Aegislash", "usage_percent": 6.62}, {"name": "Cursola", "usage_percent": 6.449}, {"name": "Torkoal", "usage_percent": 6.363}, {"name": "Cinderace", "usage_percent": 5.927}, {"name": "Gourgeist-Super", "usage_percent": 5.265}, {"name": "Charizard-Mega-Y", "usage_percent": 3.382}, {"name": "Volcarona", "usage_percent": 3.352}, {"name": "Ceruledge", "usage_percent": 2.846}, {"name": "Charizard", "usage_percent": 2.836}, {"name": "Cofagrigus", "usage_percent": 2.733}, {"name": "Infernape", "usage_percent": 1.923}, {"name": "Sableye-Mega", "usage_percent": 1.903}, {"name": "Yamask", "usage_percent": 1.184}, {"name": "Sinistcha", "usage_percent": 0.951}, {"name": "Ninetales", "usage_percent": 0.937}, {"name": "Lampent", "usage_percent": 0.935}, {"name": "Basculegion", "usage_percent": 0.914}, {"name": "Jellicent", "usage_percent": 0.81}, {"name": "Dusclops", "usage_percent": 0.7}, {"name": "Drifblim", "usage_percent": 0.653}, {"name": "Heatran", "usage_percent": 0.488}, {"name": "Blacephalon", "usage_percent": 0.461}, {"name": "Skeledirge", "usage_percent": 0.342}, {"name": "Rapidash", "usage_percent": 0.184}, {"name": "Incineroar", "usage_percent": 0.149}, {"name": "Iron Moth", "usage_percent": 0.118}, {"name": "Tauros-Paldea-Blaze", "usage_percent": 0.118}, {"name": "Polteageist", "usage_percent": 0.101}, {"name": "Doublade", "usage_percent": 0.088}, {"name": "Shedinja", "usage_percent": 0.069}, {"name": "Charizard-Mega-X", "usage_percent": 0.043}, {"name": "Typhlosion-Hisui", "usage_percent": 0.025}, {"name": "Pecharunt", "usage_percent": 0.011}, {"name": "Decidueye", "usage_percent": 0.007}, {"name": "Dusknoir", "usage_percent": 0.005}, {"name": "Oricorio-Sensu", "usage_percent": 0.003}, {"name": "Magmortar", "usage_percent": 0.002}, {"name": "Silvally-Ghost", "usage_percent": 0.0}, {"name": "Flareon", "usage_percent": 0.0}, {"name": "Arcanine", "usage_percent": 0.0}, {"name": "Oricorio", "usage_percent": 0.0}, {"name": "Delphox", "usage_percent": 0.0}, {"name": "Froslass", "usage_percent": 0.0}, {"name": "Brambleghast", "usage_percent": 0.0}, {"name": "Mismagius", "usage_percent": 0.0}, {"name": "Scovillain", "usage_percent": 0.0}, {"name": "Palossand", "usage_percent": 0.0}, {"name": "Drifloon", "usage_percent": 0.0}, {"name": "Houndstone", "usage_percent": 0.0}, {"name": "Moltres", "usage_percent": 0.0}, {"name": "Basculegion-F", "usage_percent": 0.0}, {"name": "Houndoom-Mega", "usage_percent": 0.0}, {"name": "Rotom-Heat", "usage_percent": 0.0}], "items": [{"name": "Thick Club", "id": "thickclub", "usage_percent": 99.939}, {"name": "Focus Sash", "id": "focussash", "usage_percent": 0.057}, {"name": "Life Orb", "id": "lifeorb", "usage_percent": 0.005}, {"name": "Assault Vest", "id": "assaultvest", "usage_percent": 0.0}, {"name": "nothing", "id": "nothing", "usage_percent": 0.0}], "abilities": [{"name": "Rock Head", "id": "rockhead", "usage_percent": 94.129}, {"name": "Lightning Rod", "id": "lightningrod", "usage_percent": 5.863}, {"name": "Cursed Body", "id": "cursedbody", "usage_percent": 0.007}], "natures": [{"name": "Adamant", "usage_percent": 58.291}, {"name": "Brave", "usage_percent": 27.453}, {"name": "Careful", "usage_percent": 14.034}, {"name": "Jolly", "usage_percent": 0.214}, {"name": "Hardy", "usage_percent": 0.007}, {"name": "Impish", "usage_percent": 0.0}, {"name": "Sassy", "usage_percent": 0.0}], "spreads": [{"spread": "Adamant:248/252/8/0/0/0", "usage_percent": 39.337}, {"spread": "Brave:248/252/0/0/8/0", "usage_percent": 17.973}, {"spread": "Careful:0/144/112/0/252/0", "usage_percent": 14.034}, {"spread": "Adamant:4/252/0/0/252/0", "usage_percent": 10.08}, {"spread": "Adamant:248/252/0/0/8/0", "usage_percent": 7.856}, {"spread": "Brave:252/252/0/0/4/0", "usage_percent": 6.449}, {"spread": "Brave:248/252/8/0/0/0", "usage_percent": 2.856}, {"spread": "Adamant:252/252/4/0/0/0", "usage_percent": 1.008}], "evs": {"atk": [{"ev_string": "252+ Atk", "usage_percent": 85.744}, {"ev_string": "144 Atk", "usage_percent": 14.034}, {"ev_string": "252 Atk", "usage_percent": 0.212}, {"ev_string": "219 Atk", "usage_percent": 0.007}, {"ev_string": "100 Atk", "usage_percent": 0.002}], "spa": [{"ev_string": "0- SpA", "usage_percent": 72.54}, {"ev_string": "0 SpA", "usage_percent": 27.46}, {"ev_string": "32 SpA", "usage_percent": 0.0}], "spe": [{"ev_string": "0 Spe", "usage_percent": 72.329}, {"ev_string": "0- Spe", "usage_percent": 27.453}, {"ev_string": "252+ Spe", "usage_percent": 0.214}, {"ev_string": "252 Spe", "usage_percent": 0.003}, {"ev_string": "60 Spe", "usage_percent": 0.0}], "hp_def": [{"ev_string": "248 HP / 8 Def", "usage_percent": 42.193}, {"ev_string": "248 HP / 0 Def", "usage_percent": 25.83}, {"ev_string": "0 HP / 112 Def", "usage_percent": 14.034}, {"ev_string": "4 HP / 0 Def", "usage_percent": 10.08}, {"ev_string": "252 HP / 0 Def", "usage_percent": 6.455}, {"ev_string": "252 HP / 4 Def", "usage_percent": 1.016}], "hp_spd": [{"ev_string": "248 HP / 0 SpD", "usage_percent": 42.193}, {"ev_string": "248 HP / 8 SpD", "usage_percent": 25.83}, {"ev_string": "0 HP / 252+ SpD", "usage_percent": 14.034}, {"ev_string": "4 HP / 252 SpD", "usage_percent": 10.08}, {"ev_string": "252 HP / 4 SpD", "usage_percent": 6.455}, {"ev_string": "252 HP / 0 SpD", "usage_percent": 1.016}]}, "tera_types": [{"tera_type": "Nothing", "usage_percent": 100.0}], "counters": [], "dominates": [], "rating": 1630}