{"name": "Clefable", "usage": {"name": "Clefable", "rank": 147, "usage_percent": 0.821}, "base_stats": [95, 70, 73, 95, 90, 60], "types": ["Fairy"], "possible_abilities": ["Cute Charm", "Magic Guard", "Unaware"], "moves": [{"name": "Moonblast", "id": "moonblast", "usage_percent": 75.982}, {"name": "Calm Mind", "id": "calmmind", "usage_percent": 38.608}, {"name": "Wish", "id": "wish", "usage_percent": 34.53}, {"name": "Soft-Boiled", "id": "softboiled", "usage_percent": 30.602}, {"name": "Protect", "id": "protect", "usage_percent": 25.08}, {"name": "Thunder Wave", "id": "thunderwave", "usage_percent": 20.592}, {"name": "Moonlight", "id": "moonlight", "usage_percent": 19.501}, {"name": "Flamethrower", "id": "flamethrower", "usage_percent": 19.462}, {"name": "Stealth Rock", "id": "stealthrock", "usage_percent": 17.518}, {"name": "Cosmic Power", "id": "cosmicpower", "usage_percent": 16.143}, {"name": "Toxic", "id": "toxic", "usage_percent": 14.323}, {"name": "Heal Bell", "id": "healbell", "usage_percent": 11.058}, {"name": "Stored Power", "id": "storedpower", "usage_percent": 9.785}, {"name": "Encore", "id": "encore", "usage_percent": 5.371}, {"name": "Teleport", "id": "teleport", "usage_percent": 5.266}, {"name": "Thunderbolt", "id": "thunderbolt", "usage_percent": 5.264}, {"name": "Charge Beam", "id": "chargebeam", "usage_percent": 3.99}, {"name": "Draining Kiss", "id": "drainingkiss", "usage_percent": 3.621}, {"name": "Aromatherapy", "id": "aromatherapy", "usage_percent": 3.549}, {"name": "Trick", "id": "trick", "usage_percent": 3.373}, {"name": "Knock Off", "id": "knockoff", "usage_percent": 3.27}, {"name": "Psychic", "id": "psychic", "usage_percent": 3.26}, {"name": "Fire Blast", "id": "fireblast", "usage_percent": 2.855}, {"name": "Alluring Voice", "id": "alluringvoice", "usage_percent": 2.235}, {"name": "Meteor Beam", "id": "meteorbeam", "usage_percent": 2.212}, {"name": "Misty Explosion", "id": "mistyexplosion", "usage_percent": 2.062}, {"name": "Ice Beam", "id": "icebeam", "usage_percent": 1.799}, {"name": "Reflect", "id": "reflect", "usage_percent": 1.783}, {"name": "Healing Wish", "id": "healingwish", "usage_percent": 1.773}, {"name": "Seismic Toss", "id": "seismictoss", "usage_percent": 1.325}, {"name": "Play Rough", "id": "playrough", "usage_percent": 0.964}, {"name": "Light Screen", "id": "lightscreen", "usage_percent": 0.906}, {"name": "Psyshock", "id": "psyshock", "usage_percent": 0.868}, {"name": "Metronome", "id": "metronome", "usage_percent": 0.846}, {"name": "Rest", "id": "rest", "usage_percent": 0.837}, {"name": "Fire Punch", "id": "firepunch", "usage_percent": 0.783}, {"name": "Meteor Mash", "id": "meteormash", "usage_percent": 0.765}, {"name": "Focus Punch", "id": "focuspunch", "usage_percent": 0.765}, {"name": "Sleep Talk", "id": "sleeptalk", "usage_percent": 0.671}, {"name": "Shadow Ball", "id": "shadowball", "usage_percent": 0.557}, {"name": "Chilling Water", "id": "chillingwater", "usage_percent": 0.432}, {"name": "Magic Coat", "id": "magiccoat", "usage_percent": 0.415}, {"name": "Future Sight", "id": "futuresight", "usage_percent": 0.403}, {"name": "Counter", "id": "counter", "usage_percent": 0.38}, {"name": "Thunder", "id": "thunder", "usage_percent": 0.367}, {"name": "Defense Curl", "id": "defensecurl", "usage_percent": 0.331}, {"name": "", "id": "", "usage_percent": 0.318}, {"name": "Night Shade", "id": "nightshade", "usage_percent": 0.317}, {"name": "Hyper Voice", "id": "hypervoice", "usage_percent": 0.287}, {"name": "Belly Drum", "id": "bellydrum", "usage_percent": 0.263}, {"name": "Work Up", "id": "workup", "usage_percent": 0.235}, {"name": "Sing", "id": "sing", "usage_percent": 0.162}, {"name": "Helping Hand", "id": "helpinghand", "usage_percent": 0.157}, {"name": "Follow Me", "id": "followme", "usage_percent": 0.149}, {"name": "Mystical Fire", "id": "mysticalfire", "usage_percent": 0.146}, {"name": "Brick Break", "id": "brickbreak", "usage_percent": 0.128}, {"name": "Substitute", "id": "substitute", "usage_percent": 0.127}, {"name": "Drain Punch", "id": "drainpunch", "usage_percent": 0.119}, {"name": "Tera Blast", "id": "terablast", "usage_percent": 0.107}, {"name": "Copycat", "id": "copycat", "usage_percent": 0.105}, {"name": "Safeguard", "id": "safeguard", "usage_percent": 0.104}, {"name": "Body Slam", "id": "bodyslam", "usage_percent": 0.104}, {"name": "Psych Up", "id": "psychup", "usage_percent": 0.101}, {"name": "Blizzard", "id": "blizzard", "usage_percent": 0.075}, {"name": "Dazzling Gleam", "id": "dazzlinggleam", "usage_percent": 0.072}, {"name": "Facade", "id": "facade", "usage_percent": 0.06}, {"name": "Sunny Day", "id": "sunnyday", "usage_percent": 0.052}, {"name": "Heal Pulse", "id": "healpulse", "usage_percent": 0.05}, {"name": "Double-Edge", "id": "doubleedge", "usage_percent": 0.041}, {"name": "Rain Dance", "id": "raindance", "usage_percent": 0.04}, {"name": "Present", "id": "present", "usage_percent": 0.034}, {"name": "After You", "id": "afteryou", "usage_percent": 0.032}, {"name": "Hidden Power Ground", "id": "hiddenpowerground", "usage_percent": 0.031}, {"name": "Bubble Beam", "id": "bubblebeam", "usage_percent": 0.024}, {"name": "Focus Blast", "id": "focusblast", "usage_percent": 0.022}, {"name": "Curse", "id": "curse", "usage_percent": 0.021}, {"name": "Tri Attack", "id": "triattack", "usage_percent": 0.015}, {"name": "Charm", "id": "charm", "usage_percent": 0.01}, {"name": "Last Resort", "id": "lastresort", "usage_percent": 0.005}, {"name": "Amnesia", "id": "amnesia", "usage_percent": 0.002}, {"name": "Life Dew", "id": "lifedew", "usage_percent": 0.001}, {"name": "Sweet Kiss", "id": "sweetkiss", "usage_percent": 0.0}, {"name": "Covet", "id": "covet", "usage_percent": 0.0}, {"name": "Magical Leaf", "id": "magicalleaf", "usage_percent": 0.0}, {"name": "Skill Swap", "id": "skillswap", "usage_percent": 0.0}, {"name": "Dream Eater", "id": "dreameater", "usage_percent": 0.0}, {"name": "Hidden Power Flying", "id": "hiddenpowerflying", "usage_percent": 0.0}], "teammates": [{"name": "Grimmsnarl", "usage_percent": 20.217}, {"name": "Salamence-Mega", "usage_percent": 11.674}, {"name": "Dragapult", "usage_percent": 11.22}, {"name": "Landorus-Therian", "usage_percent": 10.099}, {"name": "Venusaur-Mega", "usage_percent": 10.077}, {"name": "Landorus", "usage_percent": 8.474}, {"name": "Celesteela", "usage_percent": 8.424}, {"name": "Lucario-Mega", "usage_percent": 8.324}, {"name": "Chansey", "usage_percent": 7.897}, {"name": "Alomomola", "usage_percent": 7.476}, {"name": "Toxapex", "usage_percent": 7.315}, {"name": "Marshadow", "usage_percent": 7.126}, {"name": "Ferrothorn", "usage_percent": 6.936}, {"name": "Mewtwo", "usage_percent": 6.9}, {"name": "Yveltal", "usage_percent": 6.696}, {"name": "Necrozma-Dusk-Mane", "usage_percent": 6.127}, {"name": "Ceruledge", "usage_percent": 5.882}, {"name": "Nidoking", "usage_percent": 5.758}, {"name": "Arcanine", "usage_percent": 5.668}, {"name": "Zapdos", "usage_percent": 5.564}, {"name": "Rotom-Wash", "usage_percent": 5.555}, {"name": "Dragonite", "usage_percent": 5.449}, {"name": "Starmie", "usage_percent": 5.421}, {"name": "Gliscor", "usage_percent": 5.187}, {"name": "Corviknight", "usage_percent": 4.77}, {"name": "Charizard-Mega-X", "usage_percent": 4.661}, {"name": "Zacian-Crowned", "usage_percent": 4.514}, {"name": "Ditto", "usage_percent": 4.247}, {"name": "Garchomp", "usage_percent": 4.235}, {"name": "Rayquaza", "usage_percent": 3.978}, {"name": "Groudon-Primal", "usage_percent": 3.959}, {"name": "Greninja", "usage_percent": 3.812}, {"name": "Calyrex-Ice", "usage_percent": 3.68}, {"name": "Incineroar", "usage_percent": 3.621}, {"name": "Vaporeon", "usage_percent": 3.322}, {"name": "Zygarde", "usage_percent": 3.291}, {"name": "Arceus", "usage_percent": 3.26}, {"name": "Darmanitan-Galar", "usage_percent": 3.256}, {"name": "Clodsire", "usage_percent": 3.239}, {"name": "Iron Valiant", "usage_percent": 3.154}, {"name": "Kangaskhan-Mega", "usage_percent": 3.104}, {"name": "Volcarona", "usage_percent": 3.097}, {"name": "Blaziken-Mega", "usage_percent": 2.897}, {"name": "Chien-Pao", "usage_percent": 2.787}, {"name": "Cloyster", "usage_percent": 2.624}, {"name": "Glimmora", "usage_percent": 2.606}, {"name": "Ho-Oh", "usage_percent": 2.544}, {"name": "Flutter Mane", "usage_percent": 2.401}, {"name": "Galvantula", "usage_percent": 2.33}, {"name": "Excadrill", "usage_percent": 2.328}, {"name": "Slowbro", "usage_percent": 2.317}, {"name": "Sableye-Mega", "usage_percent": 2.309}, {"name": "Gyarados", "usage_percent": 2.292}, {"name": "Metagross-Mega", "usage_percent": 2.123}, {"name": "Alakazam", "usage_percent": 2.089}, {"name": "Heatran", "usage_percent": 2.073}, {"name": "Ting-Lu", "usage_percent": 2.04}, {"name": "Gothitelle", "usage_percent": 1.975}, {"name": "Gyarados-Mega", "usage_percent": 1.857}, {"name": "Samurott-Hisui", "usage_percent": 1.738}, {"name": "Malamar", "usage_percent": 1.734}, {"name": "Kingambit", "usage_percent": 1.715}, {"name": "Skarmory", "usage_percent": 1.706}, {"name": "Dugtrio", "usage_percent": 1.682}, {"name": "Great Tusk", "usage_percent": 1.679}, {"name": "Aegislash", "usage_percent": 1.665}, {"name": "Tyranitar", "usage_percent": 1.641}, {"name": "Alakazam-Mega", "usage_percent": 1.632}, {"name": "Blissey", "usage_percent": 1.626}, {"name": "Mew", "usage_percent": 1.604}, {"name": "Blaziken", "usage_percent": 1.598}, {"name": "Cinderace", "usage_percent": 1.563}, {"name": "Mawile-Mega", "usage_percent": 1.56}, {"name": "Conkeldurr", "usage_percent": 1.555}, {"name": "Scizor", "usage_percent": 1.55}, {"name": "Charizard-Mega-Y", "usage_percent": 1.537}, {"name": "Kyogre-Primal", "usage_percent": 1.536}, {"name": "Scizor-Mega", "usage_percent": 1.531}, {"name": "Sneasler", "usage_percent": 1.514}, {"name": "Blastoise-Mega", "usage_percent": 1.513}, {"name": "Lugia", "usage_percent": 1.501}, {"name": "Gholdengo", "usage_percent": 1.497}, {"name": "Meowscarada", "usage_percent": 1.471}, {"name": "Terapagos", "usage_percent": 1.464}, {"name": "Espathra", "usage_percent": 1.407}, {"name": "Gardevoir-Mega", "usage_percent": 1.401}, {"name": "Smeargle", "usage_percent": 1.391}, {"name": "Machamp", "usage_percent": 1.317}, {"name": "Iron Treads", "usage_percent": 1.286}, {"name": "Arceus-Dark", "usage_percent": 1.258}, {"name": "Sandslash", "usage_percent": 1.256}, {"name": "Annihilape", "usage_percent": 1.231}, {"name": "Giratina", "usage_percent": 1.201}, {"name": "Gengar", "usage_percent": 1.201}, {"name": "Aggron-Mega", "usage_percent": 1.195}, {"name": "Groudon", "usage_percent": 1.175}, {"name": "Palafin", "usage_percent": 1.174}, {"name": "Blacephalon", "usage_percent": 1.172}, {"name": "Entei", "usage_percent": 1.152}, {"name": "Tapu Koko", "usage_percent": 1.148}, {"name": "Urshifu", "usage_percent": 1.145}, {"name": "Rillaboom", "usage_percent": 1.108}, {"name": "Weezing-Galar", "usage_percent": 1.105}, {"name": "Mewtwo-Mega-Y", "usage_percent": 1.093}, {"name": "Nidoqueen", "usage_percent": 1.087}, {"name": "Shuckle", "usage_percent": 1.086}, {"name": "Kabutops", "usage_percent": 1.068}, {"name": "Zamazenta-Crowned", "usage_percent": 1.046}, {"name": "Chi-Yu", "usage_percent": 1.006}, {"name": "Chandelure", "usage_percent": 1.002}, {"name": "Lycanroc-Dusk", "usage_percent": 0.998}, {"name": "Diancie-Mega", "usage_percent": 0.995}, {"name": "Rotom-Heat", "usage_percent": 0.991}, {"name": "Dusclops", "usage_percent": 0.987}, {"name": "Dracovish", "usage_percent": 0.976}, {"name": "Kartana", "usage_percent": 0.971}, {"name": "Hatterene", "usage_percent": 0.96}, {"name": "Garganacl", "usage_percent": 0.958}, {"name": "Necrozma-Dawn-Wings", "usage_percent": 0.938}, {"name": "Kyogre", "usage_percent": 0.934}, {"name": "Slowking-Galar", "usage_percent": 0.931}, {"name": "Hippowdon", "usage_percent": 0.93}, {"name": "Snorlax", "usage_percent": 0.916}, {"name": "Hawlucha", "usage_percent": 0.907}, {"name": "Serperior", "usage_percent": 0.898}, {"name": "Eternatus", "usage_percent": 0.896}, {"name": "Pheromosa", "usage_percent": 0.895}, {"name": "Granbull", "usage_percent": 0.895}, {"name": "Pelipper", "usage_percent": 0.885}, {"name": "Ribombee", "usage_percent": 0.874}, {"name": "Wigglytuff", "usage_percent": 0.872}, {"name": "Cyclizar", "usage_percent": 0.858}, {"name": "Amoonguss", "usage_percent": 0.854}, {"name": "Milotic", "usage_percent": 0.852}, {"name": "Tyranitar-Mega", "usage_percent": 0.835}, {"name": "Venusaur", "usage_percent": 0.824}, {"name": "Azumarill", "usage_percent": 0.819}, {"name": "Xurkitree", "usage_percent": 0.809}, {"name": "Togekiss", "usage_percent": 0.804}, {"name": "Skeledirge", "usage_percent": 0.792}, {"name": "Torkoal", "usage_percent": 0.784}, {"name": "Kyurem-Black", "usage_percent": 0.778}, {"name": "Jirachi", "usage_percent": 0.768}, {"name": "Pecharunt", "usage_percent": 0.745}, {"name": "Roaring Moon", "usage_percent": 0.737}, {"name": "Lunala", "usage_percent": 0.714}, {"name": "Victini", "usage_percent": 0.71}, {"name": "Buzzwole", "usage_percent": 0.7}, {"name": "Kangaskhan", "usage_percent": 0.677}, {"name": "Dondozo", "usage_percent": 0.673}, {"name": "Mimikyu", "usage_percent": 0.668}, {"name": "Sableye", "usage_percent": 0.661}, {"name": "Seismitoad", "usage_percent": 0.658}, {"name": "Klefki", "usage_percent": 0.624}, {"name": "Palkia-Origin", "usage_percent": 0.621}, {"name": "Arceus-Ground", "usage_percent": 0.611}, {"name": "Lapras", "usage_percent": 0.61}, {"name": "Wugtrio", "usage_percent": 0.609}, {"name": "Corsola-Galar", "usage_percent": 0.609}, {"name": "Basculegion", "usage_percent": 0.605}, {"name": "Aerodactyl-Mega", "usage_percent": 0.596}, {"name": "Giratina-Origin", "usage_percent": 0.594}, {"name": "Garchomp-Mega", "usage_percent": 0.591}, {"name": "Weavile", "usage_percent": 0.591}, {"name": "Archaludon", "usage_percent": 0.589}, {"name": "Kyurem", "usage_percent": 0.578}, {"name": "Blastoise", "usage_percent": 0.576}, {"name": "Walking Wake", "usage_percent": 0.565}, {"name": "Empoleon", "usage_percent": 0.527}, {"name": "Rhyperior", "usage_percent": 0.52}, {"name": "Porygon-Z", "usage_percent": 0.517}, {"name": "Wo-Chien", "usage_percent": 0.513}, {"name": "Gallade-Mega", "usage_percent": 0.502}, {"name": "Cinccino", "usage_percent": 0.492}, {"name": "Zoroark-Hisui", "usage_percent": 0.476}, {"name": "Deoxys-Attack", "usage_percent": 0.461}, {"name": "Dedenne", "usage_percent": 0.459}, {"name": "Moltres", "usage_percent": 0.459}, {"name": "Medicham-Mega", "usage_percent": 0.457}, {"name": "Ninetales", "usage_percent": 0.453}, {"name": "Tinkaton", "usage_percent": 0.446}, {"name": "Sceptile", "usage_percent": 0.443}, {"name": "Umbreon", "usage_percent": 0.436}, {"name": "Sylveon", "usage_percent": 0.436}, {"name": "Magnezone", "usage_percent": 0.431}, {"name": "Sawk", "usage_percent": 0.43}, {"name": "Iron Thorns", "usage_percent": 0.427}, {"name": "Swampert-Mega", "usage_percent": 0.426}, {"name": "Charizard", "usage_percent": 0.418}, {"name": "Kommo-o", "usage_percent": 0.411}, {"name": "Solgaleo", "usage_percent": 0.407}, {"name": "Musharna", "usage_percent": 0.405}, {"name": "Golem", "usage_percent": 0.401}, {"name": "Haxorus", "usage_percent": 0.399}, {"name": "Regieleki", "usage_percent": 0.396}, {"name": "Tapu Lele", "usage_percent": 0.39}, {"name": "Scrafty", "usage_percent": 0.389}, {"name": "Beedrill-Mega", "usage_percent": 0.386}, {"name": "Ninetales-Alola", "usage_percent": 0.383}, {"name": "Aerodactyl", "usage_percent": 0.382}, {"name": "Latios-Mega", "usage_percent": 0.38}, {"name": "Linoone", "usage_percent": 0.371}, {"name": "Tsareena", "usage_percent": 0.371}, {"name": "Lanturn", "usage_percent": 0.371}, {"name": "Meganium", "usage_percent": 0.37}, {"name": "Urshifu-Rapid-Strike", "usage_percent": 0.364}, {"name": "Arceus-Fairy", "usage_percent": 0.348}, {"name": "Slowking", "usage_percent": 0.345}, {"name": "Eelektross", "usage_percent": 0.344}, {"name": "Ogerpon-Wellspring", "usage_percent": 0.341}, {"name": "Greedent", "usage_percent": 0.341}, {"name": "Keldeo", "usage_percent": 0.322}, {"name": "Scyther", "usage_percent": 0.314}, {"name": "Genesect", "usage_percent": 0.305}, {"name": "Muk", "usage_percent": 0.3}, {"name": "Houndstone", "usage_percent": 0.3}, {"name": "Golurk", "usage_percent": 0.3}, {"name": "Primarina", "usage_percent": 0.295}, {"name": "Reuniclus", "usage_percent": 0.295}, {"name": "Cradily", "usage_percent": 0.292}, {"name": "Deoxys-Defense", "usage_percent": 0.29}, {"name": "Bisharp", "usage_percent": 0.289}, {"name": "Hoopa-Unbound", "usage_percent": 0.288}, {"name": "Tornadus-Therian", "usage_percent": 0.286}, {"name": "Lopunny-Mega", "usage_percent": 0.281}, {"name": "Tentacruel", "usage_percent": 0.281}, {"name": "Darkrai", "usage_percent": 0.278}, {"name": "Rhydon", "usage_percent": 0.274}, {"name": "Pinsir-Mega", "usage_percent": 0.273}, {"name": "Glaceon", "usage_percent": 0.272}, {"name": "Dracozolt", "usage_percent": 0.267}, {"name": "Hydreigon", "usage_percent": 0.267}, {"name": "Obstagoon", "usage_percent": 0.262}, {"name": "Steelix-Mega", "usage_percent": 0.26}, {"name": "Shaymin-Sky", "usage_percent": 0.257}, {"name": "Mandibuzz", "usage_percent": 0.256}, {"name": "Dhelmise", "usage_percent": 0.252}, {"name": "Tapu Fini", "usage_percent": 0.25}, {"name": "Naganadel", "usage_percent": 0.249}, {"name": "Melmetal", "usage_percent": 0.248}, {"name": "Arceus-Ghost", "usage_percent": 0.242}, {"name": "Iron Crown", "usage_percent": 0.242}, {"name": "Orthworm", "usage_percent": 0.241}, {"name": "Minior", "usage_percent": 0.239}, {"name": "Magearna", "usage_percent": 0.238}, {"name": "Manectric-Mega", "usage_percent": 0.237}, {"name": "Toxtricity", "usage_percent": 0.234}, {"name": "Cetitan", "usage_percent": 0.234}, {"name": "Quagsire", "usage_percent": 0.233}, {"name": "Zygarde-10%", "usage_percent": 0.229}, {"name": "Maushold", "usage_percent": 0.226}, {"name": "Arboliva", "usage_percent": 0.224}, {"name": "Abomasnow-Mega", "usage_percent": 0.216}, {"name": "Slowbro-Mega", "usage_percent": 0.215}, {"name": "Quaquaval", "usage_percent": 0.213}, {"name": "Sigilyph", "usage_percent": 0.212}, {"name": "Infernape", "usage_percent": 0.211}, {"name": "Zekrom", "usage_percent": 0.21}, {"name": "Arceus-Psychic", "usage_percent": 0.209}, {"name": "Ogerpon-Hearthflame", "usage_percent": 0.207}, {"name": "Goodra", "usage_percent": 0.202}, {"name": "Banette-Mega", "usage_percent": 0.198}, {"name": "Alcremie", "usage_percent": 0.198}, {"name": "Mantine", "usage_percent": 0.197}, {"name": "Aggron", "usage_percent": 0.183}, {"name": "Victreebel", "usage_percent": 0.18}, {"name": "Porygon2", "usage_percent": 0.18}, {"name": "Forretress", "usage_percent": 0.177}, {"name": "Jolteon", "usage_percent": 0.176}, {"name": "Magmar", "usage_percent": 0.173}, {"name": "Exeggutor", "usage_percent": 0.166}, {"name": "Falinks", "usage_percent": 0.166}, {"name": "Pyukumuku", "usage_percent": 0.164}, {"name": "Salazzle", "usage_percent": 0.164}, {"name": "Krookodile", "usage_percent": 0.163}, {"name": "Barbaracle", "usage_percent": 0.159}, {"name": "Metagross", "usage_percent": 0.148}, {"name": "Torterra", "usage_percent": 0.147}, {"name": "Gastrodon", "usage_percent": 0.144}, {"name": "Tangrowth", "usage_percent": 0.141}, {"name": "Latios", "usage_percent": 0.141}, {"name": "Politoed", "usage_percent": 0.14}, {"name": "Venomoth", "usage_percent": 0.14}, {"name": "Sirfetch'd", "usage_percent": 0.137}, {"name": "Typhlosion", "usage_percent": 0.137}, {"name": "Crocalor", "usage_percent": 0.135}, {"name": "Tauros", "usage_percent": 0.132}, {"name": "Pinsir", "usage_percent": 0.132}, {"name": "Whimsicott", "usage_percent": 0.131}, {"name": "Vivillon", "usage_percent": 0.126}, {"name": "Raging Bolt", "usage_percent": 0.122}, {"name": "Slurpuff", "usage_percent": 0.122}, {"name": "Crawdaunt", "usage_percent": 0.12}, {"name": "Araquanid", "usage_percent": 0.119}, {"name": "Absol", "usage_percent": 0.119}, {"name": "Mismagius", "usage_percent": 0.118}, {"name": "Zeraora", "usage_percent": 0.118}, {"name": "Lilligant", "usage_percent": 0.117}, {"name": "Articuno-Galar", "usage_percent": 0.115}, {"name": "Froslass", "usage_percent": 0.115}, {"name": "Lokix", "usage_percent": 0.112}, {"name": "Roserade", "usage_percent": 0.111}, {"name": "Poliwrath", "usage_percent": 0.111}, {"name": "Swellow", "usage_percent": 0.11}, {"name": "Swalot", "usage_percent": 0.11}, {"name": "Zamazenta", "usage_percent": 0.106}, {"name": "Ursaluna-Bloodmoon", "usage_percent": 0.105}, {"name": "Dragalge", "usage_percent": 0.105}, {"name": "Fezandipiti", "usage_percent": 0.105}, {"name": "Lunatone", "usage_percent": 0.1}, {"name": "Dialga", "usage_percent": 0.1}, {"name": "Mienshao", "usage_percent": 0.095}, {"name": "Houndoom-Mega", "usage_percent": 0.091}, {"name": "Delphox", "usage_percent": 0.09}, {"name": "Cresselia", "usage_percent": 0.09}, {"name": "Heliolisk", "usage_percent": 0.09}, {"name": "Arceus-Water", "usage_percent": 0.09}, {"name": "Bronzong", "usage_percent": 0.089}, {"name": "Goodra-Hisui", "usage_percent": 0.088}, {"name": "Dunsparce", "usage_percent": 0.088}, {"name": "Eevee", "usage_percent": 0.088}, {"name": "Bastiodon", "usage_percent": 0.085}, {"name": "Comfey", "usage_percent": 0.085}, {"name": "Donphan", "usage_percent": 0.085}, {"name": "Registeel", "usage_percent": 0.084}, {"name": "Mamoswine", "usage_percent": 0.084}, {"name": "Pikachu", "usage_percent": 0.082}, {"name": "Cacturne", "usage_percent": 0.08}, {"name": "Lopunny", "usage_percent": 0.078}, {"name": "Breloom", "usage_percent": 0.078}, {"name": "Tatsugiri", "usage_percent": 0.078}, {"name": "Latias", "usage_percent": 0.077}, {"name": "Marowak", "usage_percent": 0.075}, {"name": "Dewgong", "usage_percent": 0.075}, {"name": "Deoxys-Speed", "usage_percent": 0.075}, {"name": "Emboar", "usage_percent": 0.074}, {"name": "Gallade", "usage_percent": 0.073}, {"name": "Gardevoir", "usage_percent": 0.073}, {"name": "Pincurchin", "usage_percent": 0.072}, {"name": "Thundurus", "usage_percent": 0.072}, {"name": "Gouging Fire", "usage_percent": 0.068}, {"name": "Durant", "usage_percent": 0.067}, {"name": "Eiscue", "usage_percent": 0.067}, {"name": "Espeon", "usage_percent": 0.067}, {"name": "Scream Tail", "usage_percent": 0.066}, {"name": "Seviper", "usage_percent": 0.065}, {"name": "Tropius", "usage_percent": 0.065}, {"name": "Salamence", "usage_percent": 0.057}, {"name": "Suicune", "usage_percent": 0.056}, {"name": "Magneton", "usage_percent": 0.056}, {"name": "Ursaluna", "usage_percent": 0.056}, {"name": "Armarouge", "usage_percent": 0.054}, {"name": "Talonflame", "usage_percent": 0.054}, {"name": "Pawmot", "usage_percent": 0.051}, {"name": "Kingdra", "usage_percent": 0.051}, {"name": "Kilowattrel", "usage_percent": 0.05}, {"name": "Pupitar", "usage_percent": 0.05}, {"name": "Simisage", "usage_percent": 0.05}, {"name": "Pancham", "usage_percent": 0.05}, {"name": "Carbink", "usage_percent": 0.048}, {"name": "Chimecho", "usage_percent": 0.048}, {"name": "Camerupt", "usage_percent": 0.048}, {"name": "Chesnaught", "usage_percent": 0.047}, {"name": "Altaria-Mega", "usage_percent": 0.047}, {"name": "Lycanroc", "usage_percent": 0.046}, {"name": "Pidgeot-Mega", "usage_percent": 0.045}, {"name": "Shaymin", "usage_percent": 0.045}, {"name": "Steelix", "usage_percent": 0.045}, {"name": "Honchkrow", "usage_percent": 0.045}, {"name": "Enamorus", "usage_percent": 0.045}, {"name": "Heracross-Mega", "usage_percent": 0.045}, {"name": "Audino-Mega", "usage_percent": 0.044}, {"name": "Metang", "usage_percent": 0.043}, {"name": "Clefairy", "usage_percent": 0.043}, {"name": "Gothorita", "usage_percent": 0.041}, {"name": "Rotom-Frost", "usage_percent": 0.04}, {"name": "Dialga-Origin", "usage_percent": 0.04}, {"name": "Cofagrigus", "usage_percent": 0.039}, {"name": "Arceus-Flying", "usage_percent": 0.039}, {"name": "Murkrow", "usage_percent": 0.039}, {"name": "Furfrou", "usage_percent": 0.039}, {"name": "Muk-Alola", "usage_percent": 0.037}, {"name": "Electivire", "usage_percent": 0.035}, {"name": "Feraligatr", "usage_percent": 0.035}, {"name": "Yanmega", "usage_percent": 0.034}, {"name": "Drapion", "usage_percent": 0.034}, {"name": "Butterfree", "usage_percent": 0.034}, {"name": "Abomasnow", "usage_percent": 0.034}, {"name": "Inteleon", "usage_percent": 0.032}, {"name": "Arceus-Dragon", "usage_percent": 0.032}, {"name": "Scovillain", "usage_percent": 0.032}, {"name": "Magikarp", "usage_percent": 0.032}, {"name": "Leafeon", "usage_percent": 0.031}, {"name": "Sceptile-Mega", "usage_percent": 0.031}, {"name": "Aron", "usage_percent": 0.031}, {"name": "Togedemaru", "usage_percent": 0.031}, {"name": "Lairon", "usage_percent": 0.031}, {"name": "Manaphy", "usage_percent": 0.031}, {"name": "Indeedee-F", "usage_percent": 0.031}, {"name": "Stakataka", "usage_percent": 0.03}, {"name": "Ledian", "usage_percent": 0.03}, {"name": "Mewtwo-Mega-X", "usage_percent": 0.029}, {"name": "Reshiram", "usage_percent": 0.029}, {"name": "Dodrio", "usage_percent": 0.028}, {"name": "Avalugg", "usage_percent": 0.027}, {"name": "Slaking", "usage_percent": 0.027}, {"name": "Oricorio-Pom-Pom", "usage_percent": 0.027}, {"name": "Typhlosion-Hisui", "usage_percent": 0.027}, {"name": "Zarude", "usage_percent": 0.026}, {"name": "Noivern", "usage_percent": 0.026}, {"name": "Volcanion", "usage_percent": 0.025}, {"name": "Houndoom", "usage_percent": 0.024}, {"name": "Wooper", "usage_percent": 0.023}, {"name": "Combee", "usage_percent": 0.023}, {"name": "Flamigo", "usage_percent": 0.022}, {"name": "Flareon", "usage_percent": 0.022}, {"name": "Celebi", "usage_percent": 0.021}, {"name": "Arctozolt", "usage_percent": 0.021}, {"name": "Bagon", "usage_percent": 0.021}, {"name": "Iron Moth", "usage_percent": 0.021}, {"name": "Hitmonlee", "usage_percent": 0.02}, {"name": "Ambipom", "usage_percent": 0.02}, {"name": "Articuno", "usage_percent": 0.018}, {"name": "Vileplume", "usage_percent": 0.016}, {"name": "Aromatisse", "usage_percent": 0.016}, {"name": "Golbat", "usage_percent": 0.016}, {"name": "Tauros-Paldea-Aqua", "usage_percent": 0.016}, {"name": "Iron Bundle", "usage_percent": 0.015}, {"name": "Baxcalibur", "usage_percent": 0.015}, {"name": "Ariados", "usage_percent": 0.014}, {"name": "Bellibolt", "usage_percent": 0.014}, {"name": "Frosmoth", "usage_percent": 0.012}, {"name": "Braviary", "usage_percent": 0.012}, {"name": "Wobbuffet", "usage_percent": 0.011}, {"name": "Scolipede", "usage_percent": 0.011}, {"name": "Rapidash", "usage_percent": 0.011}, {"name": "Lycanroc-Midnight", "usage_percent": 0.011}, {"name": "Polteageist", "usage_percent": 0.009}, {"name": "Omastar", "usage_percent": 0.008}, {"name": "Beedrill", "usage_percent": 0.008}, {"name": "Gigalith", "usage_percent": 0.008}, {"name": "Weezing", "usage_percent": 0.008}, {"name": "Manectric", "usage_percent": 0.007}, {"name": "Sharpedo-Mega", "usage_percent": 0.007}, {"name": "Absol-Mega", "usage_percent": 0.007}, {"name": "Dustox", "usage_percent": 0.006}, {"name": "Raichu-Alola", "usage_percent": 0.006}, {"name": "Sandaconda", "usage_percent": 0.005}, {"name": "Hoopa", "usage_percent": 0.005}, {"name": "Coalossal", "usage_percent": 0.005}, {"name": "Lilligant-Hisui", "usage_percent": 0.005}, {"name": "Toucannon", "usage_percent": 0.005}, {"name": "Flygon", "usage_percent": 0.005}, {"name": "Floatzel", "usage_percent": 0.005}, {"name": "Florges", "usage_percent": 0.005}, {"name": "Grafaiai", "usage_percent": 0.004}, {"name": "Dugtrio-Alola", "usage_percent": 0.004}, {"name": "Persian-Alola", "usage_percent": 0.004}, {"name": "Golduck", "usage_percent": 0.004}, {"name": "Iron Hands", "usage_percent": 0.004}, {"name": "Leavanny", "usage_percent": 0.003}, {"name": "Meowstic", "usage_percent": 0.003}, {"name": "Klinklang", "usage_percent": 0.002}, {"name": "Arcanine-Hisui", "usage_percent": 0.002}, {"name": "Kyurem-White", "usage_percent": 0.002}, {"name": "Zoroark", "usage_percent": 0.002}, {"name": "Exploud", "usage_percent": 0.002}, {"name": "Doublade", "usage_percent": 0.002}, {"name": "Guzzlord", "usage_percent": 0.002}, {"name": "Kleavor", "usage_percent": 0.002}, {"name": "Uxie", "usage_percent": 0.002}, {"name": "Decidueye", "usage_percent": 0.002}, {"name": "Lucario", "usage_percent": 0.002}, {"name": "Swampert", "usage_percent": 0.001}, {"name": "Drifblim", "usage_percent": 0.001}, {"name": "Slowbro-Galar", "usage_percent": 0.001}, {"name": "Drednaw", "usage_percent": 0.001}, {"name": "Fearow", "usage_percent": 0.001}, {"name": "Camerupt-Mega", "usage_percent": 0.001}, {"name": "Arceus-Electric", "usage_percent": 0.001}, {"name": "Staraptor", "usage_percent": 0.001}, {"name": "Crobat", "usage_percent": 0.001}, {"name": "Morpeko", "usage_percent": 0.001}, {"name": "Okidogi", "usage_percent": 0.001}, {"name": "Crustle", "usage_percent": 0.001}, {"name": "Zacian", "usage_percent": 0.001}, {"name": "Bellossom", "usage_percent": 0.001}, {"name": "Tapu Bulu", "usage_percent": 0.0}, {"name": "Cobalion", "usage_percent": 0.0}, {"name": "Raikou", "usage_percent": 0.0}, {"name": "Tornadus", "usage_percent": 0.0}, {"name": "Vikavolt", "usage_percent": 0.0}, {"name": "Vanilluxe", "usage_percent": 0.0}, {"name": "Garbodor", "usage_percent": 0.0}, {"name": "Rapidash-Galar", "usage_percent": 0.0}, {"name": "Kadabra", "usage_percent": 0.0}, {"name": "Diancie", "usage_percent": 0.0}, {"name": "Rampardos", "usage_percent": 0.0}, {"name": "Boltund", "usage_percent": 0.0}, {"name": "Toedscruel", "usage_percent": 0.0}, {"name": "Liepard", "usage_percent": 0.0}, {"name": "Purugly", "usage_percent": 0.0}, {"name": "Komala", "usage_percent": 0.0}, {"name": "Wormadam-Trash", "usage_percent": 0.0}, {"name": "Bewear", "usage_percent": 0.0}, {"name": "Beheeyem", "usage_percent": 0.0}, {"name": "Lurantis", "usage_percent": 0.0}, {"name": "Gligar", "usage_percent": 0.0}, {"name": "Indeedee", "usage_percent": 0.0}, {"name": "Palpitoad", "usage_percent": 0.0}, {"name": "Shiinotic", "usage_percent": 0.0}, {"name": "Nihilego", "usage_percent": 0.0}, {"name": "Drampa", "usage_percent": 0.0}, {"name": "Oricorio-Sensu", "usage_percent": 0.0}, {"name": "Tyrantrum", "usage_percent": 0.0}, {"name": "Togetic", "usage_percent": 0.0}, {"name": "Munchlax", "usage_percent": 0.0}, {"name": "Altaria", "usage_percent": 0.0}, {"name": "Bombirdier", "usage_percent": 0.0}, {"name": "Vespiquen", "usage_percent": 0.0}, {"name": "Hydrapple", "usage_percent": 0.0}, {"name": "Oranguru", "usage_percent": 0.0}, {"name": "Mr. Rime", "usage_percent": 0.0}, {"name": "Ampharos", "usage_percent": 0.0}, {"name": "Ludicolo", "usage_percent": 0.0}, {"name": "Luxray", "usage_percent": 0.0}, {"name": "Ogerpon-Cornerstone", "usage_percent": 0.0}, {"name": "Bibarel", "usage_percent": 0.0}, {"name": "Delcatty", "usage_percent": 0.0}, {"name": "Sawsbuck", "usage_percent": 0.0}, {"name": "Miltank", "usage_percent": 0.0}, {"name": "Ampharos-Mega", "usage_percent": 0.0}, {"name": "Clawitzer", "usage_percent": 0.0}, {"name": "Masquerain", "usage_percent": 0.0}, {"name": "Delibird", "usage_percent": 0.0}, {"name": "Simipour", "usage_percent": 0.0}, {"name": "Palkia", "usage_percent": 0.0}, {"name": "Vullaby", "usage_percent": 0.0}, {"name": "Ponyta", "usage_percent": 0.0}, {"name": "Cubone", "usage_percent": 0.0}, {"name": "Monferno", "usage_percent": 0.0}, {"name": "Golem-Alola", "usage_percent": 0.0}, {"name": "Hitmonchan", "usage_percent": 0.0}, {"name": "Lombre", "usage_percent": 0.0}, {"name": "empty", "usage_percent": 0.0}, {"name": "Dachsbun", "usage_percent": 0.0}], "items": [{"name": "Leftovers", "id": "leftovers", "usage_percent": 66.316}, {"name": "Life Orb", "id": "lifeorb", "usage_percent": 6.954}, {"name": "Heavy-Duty Boots", "id": "heavydutyboots", "usage_percent": 5.111}, {"name": "Sitrus Berry", "id": "sitrusberry", "usage_percent": 3.717}, {"name": "Lagging Tail", "id": "laggingtail", "usage_percent": 2.707}, {"name": "Lum Berry", "id": "lumberry", "usage_percent": 2.537}, {"name": "Rocky Helmet", "id": "rockyhelmet", "usage_percent": 2.48}, {"name": "Kee Berry", "id": "keeberry", "usage_percent": 1.556}, {"name": "Power Herb", "id": "powerherb", "usage_percent": 1.378}, {"name": "Focus Sash", "id": "focussash", "usage_percent": 0.994}, {"name": "Red Card", "id": "redcard", "usage_percent": 0.801}, {"name": "Assault Vest", "id": "assaultvest", "usage_percent": 0.791}, {"name": "Choice Band", "id": "choiceband", "usage_percent": 0.765}, {"name": "nothing", "id": "nothing", "usage_percent": 0.732}, {"name": "Sticky Barb", "id": "stickybarb", "usage_percent": 0.547}, {"name": "Fairy Feather", "id": "fairyfeather", "usage_percent": 0.456}, {"name": "Weakness Policy", "id": "weaknesspolicy", "usage_percent": 0.364}, {"name": "Choice Scarf", "id": "choicescarf", "usage_percent": 0.343}, {"name": "Black Sludge", "id": "blacksludge", "usage_percent": 0.333}, {"name": "Air Balloon", "id": "airballoon", "usage_percent": 0.307}, {"name": "Safety Goggles", "id": "safetygoggles", "usage_percent": 0.189}, {"name": "Light Clay", "id": "lightclay", "usage_percent": 0.137}, {"name": "Kebia Berry", "id": "kebiaberry", "usage_percent": 0.092}, {"name": "Big Root", "id": "bigroot", "usage_percent": 0.072}, {"name": "Toxic Orb", "id": "toxicorb", "usage_percent": 0.056}, {"name": "Covert Cloak", "id": "covertcloak", "usage_percent": 0.048}, {"name": "Heat Rock", "id": "heatrock", "usage_percent": 0.047}, {"name": "Chesto Berry", "id": "chestoberry", "usage_percent": 0.045}, {"name": "Firium Z", "id": "firiumz", "usage_percent": 0.04}, {"name": "Mental Herb", "id": "mentalherb", "usage_percent": 0.032}, {"name": "White Herb", "id": "whiteherb", "usage_percent": 0.027}, {"name": "Berry Juice", "id": "berryjuice", "usage_percent": 0.008}, {"name": "Choice Specs", "id": "choicespecs", "usage_percent": 0.007}, {"name": "Flame Orb", "id": "flameorb", "usage_percent": 0.004}, {"name": "Metronome", "id": "metronome", "usage_percent": 0.003}, {"name": "Eviolite", "id": "eviolite", "usage_percent": 0.003}, {"name": "Expert Belt", "id": "expertbelt", "usage_percent": 0.001}, {"name": "Petaya Berry", "id": "petayaberry", "usage_percent": 0.0}, {"name": "Babiri Berry", "id": "babiriberry", "usage_percent": 0.0}, {"name": "Mirror Herb", "id": "mirrorherb", "usage_percent": 0.0}, {"name": "Silk Scarf", "id": "silkscarf", "usage_percent": 0.0}, {"name": "Wide Lens", "id": "widelens", "usage_percent": 0.0}], "abilities": [{"name": "Unaware", "id": "unaware", "usage_percent": 58.8}, {"name": "Magic Guard", "id": "magicguard", "usage_percent": 38.968}, {"name": "Cute Charm", "id": "cutecharm", "usage_percent": 2.232}], "natures": [{"name": "Bold", "usage_percent": 47.51}, {"name": "Calm", "usage_percent": 36.617}, {"name": "Modest", "usage_percent": 7.151}, {"name": "Hardy", "usage_percent": 1.976}, {"name": "Quiet", "usage_percent": 1.821}, {"name": "Sassy", "usage_percent": 1.61}, {"name": "Relaxed", "usage_percent": 0.959}, {"name": "Adamant", "usage_percent": 0.914}, {"name": "Careful", "usage_percent": 0.782}, {"name": "Impish", "usage_percent": 0.281}, {"name": "Brave", "usage_percent": 0.114}, {"name": "Serious", "usage_percent": 0.083}, {"name": "Hasty", "usage_percent": 0.075}, {"name": "Timid", "usage_percent": 0.055}, {"name": "Docile", "usage_percent": 0.029}, {"name": "Lax", "usage_percent": 0.011}, {"name": "Mild", "usage_percent": 0.007}, {"name": "Rash", "usage_percent": 0.004}, {"name": "Jolly", "usage_percent": 0.0}], "spreads": [{"spread": "Bold:252/0/252/0/4/0", "usage_percent": 15.084}, {"spread": "Bold:252/0/252/4/0/0", "usage_percent": 8.651}, {"spread": "Calm:252/0/6/0/252/0", "usage_percent": 7.842}, {"spread": "Calm:252/0/0/4/252/0", "usage_percent": 7.753}, {"spread": "Calm:252/0/4/0/252/0", "usage_percent": 5.382}, {"spread": "Calm:252/0/0/0/252/0", "usage_percent": 4.337}, {"spread": "Modest:252/0/0/252/4/0", "usage_percent": 4.263}, {"spread": "Bold:4/0/252/0/252/0", "usage_percent": 2.702}, {"spread": "Calm:6/0/252/0/252/0", "usage_percent": 2.197}, {"spread": "Bold:252/0/148/12/96/0", "usage_percent": 2.114}, {"spread": "Calm:252/0/56/4/196/0", "usage_percent": 1.64}, {"spread": "Bold:0/0/252/4/252/0", "usage_percent": 1.419}, {"spread": "Bold:248/0/252/0/8/0", "usage_percent": 1.331}, {"spread": "Quiet:248/0/164/96/0/0", "usage_percent": 1.31}, {"spread": "Bold:252/0/152/0/104/0", "usage_percent": 1.243}, {"spread": "Bold:252/0/196/0/0/60", "usage_percent": 1.219}, {"spread": "Bold:188/0/148/64/108/0", "usage_percent": 1.068}, {"spread": "Bold:248/0/148/16/96/0", "usage_percent": 1.038}], "evs": {"atk": [{"ev_string": "0- Atk", "usage_percent": 90.877}, {"ev_string": "0 Atk", "usage_percent": 6.53}, {"ev_string": "4 Atk", "usage_percent": 0.972}, {"ev_string": "252+ Atk", "usage_percent": 0.924}, {"ev_string": "252- Atk", "usage_percent": 0.239}], "spa": [{"ev_string": "0 SpA", "usage_percent": 56.244}, {"ev_string": "4 SpA", "usage_percent": 23.585}, {"ev_string": "252+ SpA", "usage_percent": 5.123}, {"ev_string": "12 SpA", "usage_percent": 2.308}, {"ev_string": "252 SpA", "usage_percent": 1.767}, {"ev_string": "0- SpA", "usage_percent": 1.584}, {"ev_string": "96+ SpA", "usage_percent": 1.31}, {"ev_string": "16 SpA", "usage_percent": 1.199}, {"ev_string": "64 SpA", "usage_percent": 1.068}], "spe": [{"ev_string": "0 Spe", "usage_percent": 90.638}, {"ev_string": "0- Spe", "usage_percent": 3.983}, {"ev_string": "60 Spe", "usage_percent": 1.32}, {"ev_string": "4 Spe", "usage_percent": 1.103}, {"ev_string": "252 Spe", "usage_percent": 0.707}], "hp_def": [{"ev_string": "252 HP / 252+ Def", "usage_percent": 25.51}, {"ev_string": "252 HP / 0 Def", "usage_percent": 19.121}, {"ev_string": "252 HP / 6 Def", "usage_percent": 7.842}, {"ev_string": "252 HP / 4 Def", "usage_percent": 6.528}, {"ev_string": "4 HP / 252+ Def", "usage_percent": 2.702}, {"ev_string": "6 HP / 252 Def", "usage_percent": 2.197}, {"ev_string": "252 HP / 148+ Def", "usage_percent": 2.114}, {"ev_string": "252 HP / 56 Def", "usage_percent": 1.64}, {"ev_string": "248 HP / 252+ Def", "usage_percent": 1.525}, {"ev_string": "0 HP / 252+ Def", "usage_percent": 1.463}, {"ev_string": "252 HP / 252 Def", "usage_percent": 1.419}, {"ev_string": "252 HP / 196+ Def", "usage_percent": 1.383}, {"ev_string": "248 HP / 164 Def", "usage_percent": 1.31}, {"ev_string": "252 HP / 152+ Def", "usage_percent": 1.243}, {"ev_string": "252 HP / 120 Def", "usage_percent": 1.071}, {"ev_string": "188 HP / 148+ Def", "usage_percent": 1.068}, {"ev_string": "248 HP / 148+ Def", "usage_percent": 1.038}], "hp_spd": [{"ev_string": "252 HP / 252+ SpD", "usage_percent": 26.733}, {"ev_string": "252 HP / 4 SpD", "usage_percent": 20.079}, {"ev_string": "252 HP / 0 SpD", "usage_percent": 13.553}, {"ev_string": "4 HP / 252 SpD", "usage_percent": 2.849}, {"ev_string": "252 HP / 252 SpD", "usage_percent": 2.645}, {"ev_string": "252 HP / 96 SpD", "usage_percent": 2.636}, {"ev_string": "6 HP / 252+ SpD", "usage_percent": 2.197}, {"ev_string": "248 HP / 0 SpD", "usage_percent": 1.646}, {"ev_string": "252 HP / 196+ SpD", "usage_percent": 1.64}, {"ev_string": "252 HP / 84 SpD", "usage_percent": 1.605}, {"ev_string": "0 HP / 252 SpD", "usage_percent": 1.545}, {"ev_string": "252 HP / 104 SpD", "usage_percent": 1.467}, {"ev_string": "252 HP / 0+ SpD", "usage_percent": 1.343}, {"ev_string": "248 HP / 8 SpD", "usage_percent": 1.331}, {"ev_string": "252 HP / 12 SpD", "usage_percent": 1.106}, {"ev_string": "188 HP / 108 SpD", "usage_percent": 1.068}, {"ev_string": "248 HP / 96 SpD", "usage_percent": 1.038}]}, "tera_types": [{"tera_type": "Fairy", "usage_percent": 53.833}, {"tera_type": "Steel", "usage_percent": 21.552}, {"tera_type": "Ghost", "usage_percent": 7.063}, {"tera_type": "Water", "usage_percent": 5.051}, {"tera_type": "Fire", "usage_percent": 3.92}, {"tera_type": "Psychic", "usage_percent": 2.601}, {"tera_type": "Poison", "usage_percent": 2.401}, {"tera_type": "Normal", "usage_percent": 1.8}, {"tera_type": "Dark", "usage_percent": 0.753}, {"tera_type": "Electric", "usage_percent": 0.261}, {"tera_type": "Ice", "usage_percent": 0.244}, {"tera_type": "Stellar", "usage_percent": 0.165}, {"tera_type": "Dragon", "usage_percent": 0.134}, {"tera_type": "Grass", "usage_percent": 0.1}, {"tera_type": "Ground", "usage_percent": 0.081}, {"tera_type": "Nothing", "usage_percent": 0.04}, {"tera_type": "Fighting", "usage_percent": 0.0}], "counters": [{"name": "Zacian-Crowned", "score": 94.105}, {"name": "Groudon-Primal", "score": 86.063}, {"name": "Kyogre-Primal", "score": 83.597}, {"name": "Necrozma-Dusk-Mane", "score": 79.534}, {"name": "Eternatus", "score": 74.205}], "dominates": [{"name": "Yveltal", "score": 70.085}, {"name": "Zygarde", "score": 63.816}, {"name": "Ho-Oh", "score": 50.761}, {"name": "Marshadow", "score": 50.137}], "rating": 1500}